Workbook

Sheet NOTES
A1: Sources (as of Feb-2019)
A3: 1 | B3: NFIB | C3: http://www.nfib-sbet.org/indicators/
C4: Historical data available in Excel format BUT it is sometimes delayed.
A5: 2 | B5: Investing.com | C5: https://www.investing.com/economic-calendar/nfib-small-business-optimism-537
C6: Another way to view the entire historical dataset, and up to date. However the only way to get all of this data from the website is manually. The easiest way to do that is to copy and paste the data. Note this only provides data for the headline index.
A11: Updating (Monthly)
A13: 1 | B13: NFIB SBO Core Index
C14: Copy down (autofill) cells in columns A-D down to a new row to input new data. Replace the data in column B for the new month.
C15: Double check the historical data in the report for any backwards revisions and edit data as necessary.
A16: 2 | B16: SBO_vs_GDP
C17: Not required - more a proof of concept. But if you do update it then:
C18: Copy down (autofill) cells in columns A-F down to a new row. Backfill GDP data in column E observed from FRED calculate the GDP YoY percentage change in column F. Note GDP data is quarterly and so one data point is required for every 3 months.
C19: Columns A to D will auto update based on data in "NFIB SBO Core Index" sheet
A20: 3 | B20: SBO_vs_SP500
C21: Not required - more a proof of concept. But if you do update it then:
C22: Copy down (autofill) cells in columns A-F down to a new row. Backfill S&P500 data in column E observed from Yahoo Finance (or other source) and calculate the S&P500 YoY percentage change in column F.
C23: Columns A to D will auto update based on data in "NFIB SBO Core Index" sheet
A24: 4 | B24: SBO_Leading_vs_GDP
C25: Not required - more a proof of concept. But if you do update it then:
C26: Copy down (autofill) cells in columns A-F down to a new row. Backfill GDP data in column E observed from FRED calculate the GDP YoY percentage change in column F. Note GDP data is quarterly and so one data point is required for every 3 months.
C27: Columns A to D will auto update based on data in core index and leading indices sheets
A28: 5 | B28: SBO_Leading_vs_SP500
C29: Not required - more a proof of concept. But if you do update it then:
C30: Copy down (autofill) cells in columns A-F down to a new row. Backfill S&P500 data in column E observed from Yahoo Finance (or other source) and calculate the S&P500 YoY percentage change in column F.
C31: Columns A to D will auto update based on data in core index and leading indices sheets
A32: 6 | B32: Sub-Indices
C33: Go to | D33: http://www.nfib-sbet.org/indicators/
C34: With the indicator set to Small Business Optimism, select the sub-index you wish to update from the indicator selector drop-down menu.
C35: Click "Show Results" (it can take a while to load)
C36: Observe lastest result and update the sub-index accordingly, or download the entire dataset and update.
D37: Note, if you download the historical dataset in Excel form you will need to transform the values from Text to Number format
A40: Index Explanation
B41: Small Business Optimism | C41: The Index of Small Business Optimism consists of 10 equally weighted and seasonally adjusted variables. The monthly change of each variable contributes proportionally to the overall monthly change in the Index.
B42: Plans to Increase Employment | C42: The percent of respondents who plan to "increase" their number of employees minus those who plan to "decrease" their number of employees in the next three months.
B43: Plans to Make Capital Outlays | C43: The percent of respondents planning a capital expenditure during the next three to six months.
B44: Plans to Increase Inventories | C44: The percent of respondents who plan to "increase" inventories minus those who plan to "decrease" inventories in the next three to six months.
B45: Expect Economy to Improve | C45: The percent of respondents who think general business condition will be "better" minus those who think it will be "worse" six months from now. Example: A net, negative 28 percent means 28 percent more small business owners think that general business conditions will be worse than those who think it will be better six months from now.
B46: Expect Retail Sales Higher | C46: The percent of respondents who think sales will be "higher" minus those who think sales will be "lower" during the next three months.
B47: Current Inventory | C47: The percent of respondents who report that their inventories are currently "too low" minus those who report their inventories are currently "too large".
B48: Current Job Openings | C48: The percent of respondents with a position they are currently not able to fill.
B49: Expected Credit Conditions | C49: The percent of respondents who think that credit conditions will be "easier" minus those who think credit conditions will be "harder" during the next three months.
B50: Now a Good Time to Expand | C50: Percent of respondents who think the next three months will be a good time for small businesses to expand.
B51: Earnings Trends | C51: The percent of respondents who report "higher" earning minus those who report "lower" earnings in the last three months compared to the prior three months.

Sheet NFIB SBO Core Index
A1: Date | B1: Small Business Optimism Index | C1: Small Business Optimism Index MoM | D1: Small Business Optimism Index YoY
A2: 31443 | B2: 100.285
A3: 31471 | B3: 99.7915 | C3: =B3-B2 -> -0.4935
A4: 31502 | B4: 101.463 | C4: =B4-B3 -> 1.6715
A5: 31532 | B5: 101.015 | C5: =B5-B4 -> -0.448
A6: 31563 | B6: 101.956 | C6: =B6-B5 -> 0.941
A7: 31593 | B7: 101.289 | C7: =B7-B6 -> -0.667
A8: 31624 | B8: 99.8372 | C8: =B8-B7 -> -1.4518
A9: 31655 | B9: 98.8144 | C9: =B9-B8 -> -1.0228
A10: 31685 | B10: 98.5861 | C10: =B10-B9 -> -0.2283
A11: 31716 | B11: 98.7596 | C11: =B11-B10 -> 0.1735
A12: 31746 | B12: 97.536 | C12: =B12-B11 -> -1.2236
A13: 31777 | B13: 100.668 | C13: =B13-B12 -> 3.132
A14: 31808 | B14: 100.102 | C14: =B14-B13 -> -0.566 | D14: =B14-B2 -> -0.183
A15: 31836 | B15: 100.613 | C15: =B15-B14 -> 0.511 | D15: =B15-B3 -> 0.8215
A16: 31867 | B16: 101.189 | C16: =B16-B15 -> 0.576 | D16: =B16-B4 -> -0.274
A17: 31897 | B17: 100.102 | C17: =B17-B16 -> -1.087 | D17: =B17-B5 -> -0.913
A18: 31928 | B18: 99.8554 | C18: =B18-B17 -> -0.2466 | D18: =B18-B6 -> -2.1006
A19: 31958 | B19: 101.746 | C19: =B19-B18 -> 1.8906 | D19: =B19-B7 -> 0.457
A20: 31989 | B20: 102.485 | C20: =B20-B19 -> 0.739 | D20: =B20-B8 -> 2.6478
A21: 32020 | B21: 103.745 | C21: =B21-B20 -> 1.26 | D21: =B21-B9 -> 4.9306
A22: 32050 | B22: 102.421 | C22: =B22-B21 -> -1.324 | D22: =B22-B10 -> 3.8349
A23: 32081 | B23: 101.59 | C23: =B23-B22 -> -0.831 | D23: =B23-B11 -> 2.8304
A24: 32111 | B24: 98.6318 | C24: =B24-B23 -> -2.9582 | D24: =B24-B12 -> 1.0958
A25: 32142 | B25: 100.029 | C25: =B25-B24 -> 1.3972 | D25: =B25-B13 -> -0.639
... A421: 44196 | B421: 95.708 | C421: =B421-B420 -> -5.479 | D421: =B421-B409 -> -6.575

Sheet SBO_vs_GDP
A1: Date | B1: Small Business Optimism Index | C1: Small Business Optimism Index MoM | D1: Small Business Optimism Index YoY | E1: US Real GDP, Billions 2012 USD, Seasonally Adjusted | F1: GDP YoY %
A2: ='NFIB SBO Core Index'!A2 -> 31443 | B2: =VLOOKUP(A2,'NFIB SBO Core Index'!A:B,2,FALSE) -> 100.285
A3: ='NFIB SBO Core Index'!A3 -> 31471 | B3: =VLOOKUP(A3,'NFIB SBO Core Index'!A:B,2,FALSE) -> 99.7915 | C3: =B3-B2 -> -0.4935
A4: ='NFIB SBO Core Index'!A4 -> 31502 | B4: =VLOOKUP(A4,'NFIB SBO Core Index'!A:B,2,FALSE) -> 101.463 | C4: =B4-B3 -> 1.6715 | E4: 8148.603
A5: ='NFIB SBO Core Index'!A5 -> 31532 | B5: =VLOOKUP(A5,'NFIB SBO Core Index'!A:B,2,FALSE) -> 101.015 | C5: =B5-B4 -> -0.448
A6: ='NFIB SBO Core Index'!A6 -> 31563 | B6: =VLOOKUP(A6,'NFIB SBO Core Index'!A:B,2,FALSE) -> 101.956 | C6: =B6-B5 -> 0.941
A7: ='NFIB SBO Core Index'!A7 -> 31593 | B7: =VLOOKUP(A7,'NFIB SBO Core Index'!A:B,2,FALSE) -> 101.289 | C7: =B7-B6 -> -0.667 | E7: 8185.303
A8: ='NFIB SBO Core Index'!A8 -> 31624 | B8: =VLOOKUP(A8,'NFIB SBO Core Index'!A:B,2,FALSE) -> 99.8372 | C8: =B8-B7 -> -1.4518
A9: ='NFIB SBO Core Index'!A9 -> 31655 | B9: =VLOOKUP(A9,'NFIB SBO Core Index'!A:B,2,FALSE) -> 98.8144 | C9: =B9-B8 -> -1.0228
A10: ='NFIB SBO Core Index'!A10 -> 31685 | B10: =VLOOKUP(A10,'NFIB SBO Core Index'!A:B,2,FALSE) -> 98.5861 | C10: =B10-B9 -> -0.2283 | E10: 8263.639
A11: ='NFIB SBO Core Index'!A11 -> 31716 | B11: =VLOOKUP(A11,'NFIB SBO Core Index'!A:B,2,FALSE) -> 98.7596 | C11: =B11-B10 -> 0.1735
A12: ='NFIB SBO Core Index'!A12 -> 31746 | B12: =VLOOKUP(A12,'NFIB SBO Core Index'!A:B,2,FALSE) -> 97.536 | C12: =B12-B11 -> -1.2236
A13: ='NFIB SBO Core Index'!A13 -> 31777 | B13: =VLOOKUP(A13,'NFIB SBO Core Index'!A:B,2,FALSE) -> 100.668 | C13: =B13-B12 -> 3.132 | E13: 8308.021
A14: ='NFIB SBO Core Index'!A14 -> 31808 | B14: =VLOOKUP(A14,'NFIB SBO Core Index'!A:B,2,FALSE) -> 100.102 | C14: =B14-B13 -> -0.566 | D14: =B14-B2 -> -0.183
A15: ='NFIB SBO Core Index'!A15 -> 31836 | B15: =VLOOKUP(A15,'NFIB SBO Core Index'!A:B,2,FALSE) -> 100.613 | C15: =B15-B14 -> 0.511 | D15: =B15-B3 -> 0.8215
A16: ='NFIB SBO Core Index'!A16 -> 31867 | B16: =VLOOKUP(A16,'NFIB SBO Core Index'!A:B,2,FALSE) -> 101.189 | C16: =B16-B15 -> 0.576 | D16: =B16-B4 -> -0.274 | E16: 8369.93 | F16: =(E16-E4)/E4 -> 0.027161343
A17: ='NFIB SBO Core Index'!A17 -> 31897 | B17: =VLOOKUP(A17,'NFIB SBO Core Index'!A:B,2,FALSE) -> 100.102 | C17: =B17-B16 -> -1.087 | D17: =B17-B5 -> -0.913
A18: ='NFIB SBO Core Index'!A18 -> 31928 | B18: =VLOOKUP(A18,'NFIB SBO Core Index'!A:B,2,FALSE) -> 99.8554 | C18: =B18-B17 -> -0.2466 | D18: =B18-B6 -> -2.1006
A19: ='NFIB SBO Core Index'!A19 -> 31958 | B19: =VLOOKUP(A19,'NFIB SBO Core Index'!A:B,2,FALSE) -> 101.746 | C19: =B19-B18 -> 1.8906 | D19: =B19-B7 -> 0.457 | E19: 8460.233 | F19: =(E19-E7)/E7 -> 0.03358825
A20: ='NFIB SBO Core Index'!A20 -> 31989 | B20: =VLOOKUP(A20,'NFIB SBO Core Index'!A:B,2,FALSE) -> 102.485 | C20: =B20-B19 -> 0.739 | D20: =B20-B8 -> 2.6478
A21: ='NFIB SBO Core Index'!A21 -> 32020 | B21: =VLOOKUP(A21,'NFIB SBO Core Index'!A:B,2,FALSE) -> 103.745 | C21: =B21-B20 -> 1.26 | D21: =B21-B9 -> 4.9306
A22: ='NFIB SBO Core Index'!A22 -> 32050 | B22: =VLOOKUP(A22,'NFIB SBO Core Index'!A:B,2,FALSE) -> 102.421 | C22: =B22-B21 -> -1.324 | D22: =B22-B10 -> 3.8349 | E22: 8533.635 | F22: =(E22-E10)/E10 -> 0.032672773
A23: ='NFIB SBO Core Index'!A23 -> 32081 | B23: =VLOOKUP(A23,'NFIB SBO Core Index'!A:B,2,FALSE) -> 101.59 | C23: =B23-B22 -> -0.831 | D23: =B23-B11 -> 2.8304
A24: ='NFIB SBO Core Index'!A24 -> 32111 | B24: =VLOOKUP(A24,'NFIB SBO Core Index'!A:B,2,FALSE) -> 98.6318 | C24: =B24-B23 -> -2.9582 | D24: =B24-B12 -> 1.0958
A25: ='NFIB SBO Core Index'!A25 -> 32142 | B25: =VLOOKUP(A25,'NFIB SBO Core Index'!A:B,2,FALSE) -> 100.029 | C25: =B25-B24 -> 1.3972 | D25: =B25-B13 -> -0.639 | E25: 8680.162 | F25: =(E25-E13)/E13 -> 0.044792978
A26: ='NFIB SBO Core Index'!A26 -> 32173 | B26: =VLOOKUP(A26,'NFIB SBO Core Index'!A:B,2,FALSE) -> 100.376 | C26: =B26-B25 -> 0.347 | D26: =B26-B14 -> 0.274
A27: ='NFIB SBO Core Index'!A27 -> 32202 | B27: =VLOOKUP(A27,'NFIB SBO Core Index'!A:B,2,FALSE) -> 99.061 | C27: =B27-B26 -> -1.315 | D27: =B27-B15 -> -1.552
A28: ='NFIB SBO Core Index'!A28 -> 32233 | B28: =VLOOKUP(A28,'NFIB SBO Core Index'!A:B,2,FALSE) -> 101.554 | C28: =B28-B27 -> 2.493 | D28: =B28-B16 -> 0.365 | E28: 8725.006 | F28: =(E28-E16)/E16 -> 0.042422816
A29: ='NFIB SBO Core Index'!A29 -> 32263 | B29: =VLOOKUP(A29,'NFIB SBO Core Index'!A:B,2,FALSE) -> 100.65 | C29: =B29-B28 -> -0.904 | D29: =B29-B17 -> 0.548
A30: ='NFIB SBO Core Index'!A30 -> 32294 | B30: =VLOOKUP(A30,'NFIB SBO Core Index'!A:B,2,FALSE) -> 100.951 | C30: =B30-B29 -> 0.301 | D30: =B30-B18 -> 1.0956
A31: ='NFIB SBO Core Index'!A31 -> 32324 | B31: =VLOOKUP(A31,'NFIB SBO Core Index'!A:B,2,FALSE) -> 101.654 | C31: =B31-B30 -> 0.703 | D31: =B31-B19 -> -0.092 | E31: 8839.641 | F31: =(E31-E19)/E19 -> 0.044846046
A32: ='NFIB SBO Core Index'!A32 -> 32355 | B32: =VLOOKUP(A32,'NFIB SBO Core Index'!A:B,2,FALSE) -> 100.111 | C32: =B32-B31 -> -1.543 | D32: =B32-B20 -> -2.374
A33: ='NFIB SBO Core Index'!A33 -> 32386 | B33: =VLOOKUP(A33,'NFIB SBO Core Index'!A:B,2,FALSE) -> 101.645 | C33: =B33-B32 -> 1.534 | D33: =B33-B21 -> -2.1
A34: ='NFIB SBO Core Index'!A34 -> 32416 | B34: =VLOOKUP(A34,'NFIB SBO Core Index'!A:B,2,FALSE) -> 100.778 | C34: =B34-B33 -> -0.867 | D34: =B34-B22 -> -1.643 | E34: 8891.435 | F34: =(E34-E22)/E22 -> 0.041928205
A35: ='NFIB SBO Core Index'!A35 -> 32447 | B35: =VLOOKUP(A35,'NFIB SBO Core Index'!A:B,2,FALSE) -> 102.138 | C35: =B35-B34 -> 1.36 | D35: =B35-B23 -> 0.548
A36: ='NFIB SBO Core Index'!A36 -> 32477 | B36: =VLOOKUP(A36,'NFIB SBO Core Index'!A:B,2,FALSE) -> 101.828 | C36: =B36-B35 -> -0.31 | D36: =B36-B24 -> 3.1962
A37: ='NFIB SBO Core Index'!A37 -> 32508 | B37: =VLOOKUP(A37,'NFIB SBO Core Index'!A:B,2,FALSE) -> 100.485 | C37: =B37-B36 -> -1.343 | D37: =B37-B25 -> 0.456 | E37: 9009.913 | F37: =(E37-E25)/E25 -> 0.037989038
A38: ='NFIB SBO Core Index'!A38 -> 32539 | B38: =VLOOKUP(A38,'NFIB SBO Core Index'!A:B,2,FALSE) -> 101.289 | C38: =B38-B37 -> 0.804 | D38: =B38-B26 -> 0.913
A39: ='NFIB SBO Core Index'!A39 -> 32567 | B39: =VLOOKUP(A39,'NFIB SBO Core Index'!A:B,2,FALSE) -> 101.892 | C39: =B39-B38 -> 0.603 | D39: =B39-B27 -> 2.831
A40: ='NFIB SBO Core Index'!A40 -> 32598 | B40: =VLOOKUP(A40,'NFIB SBO Core Index'!A:B,2,FALSE) -> 101.371 | C40: =B40-B39 -> -0.521 | D40: =B40-B28 -> -0.183 | E40: 9101.508 | F40: =(E40-E28)/E28 -> 0.043152062
A41: ='NFIB SBO Core Index'!A41 -> 32628 | B41: =VLOOKUP(A41,'NFIB SBO Core Index'!A:B,2,FALSE) -> 98.0017 | C41: =B41-B40 -> -3.3693 | D41: =B41-B29 -> -2.6483
A42: ='NFIB SBO Core Index'!A42 -> 32659 | B42: =VLOOKUP(A42,'NFIB SBO Core Index'!A:B,2,FALSE) -> 97.2985 | C42: =B42-B41 -> -0.7032 | D42: =B42-B30 -> -3.6525
A43: ='NFIB SBO Core Index'!A43 -> 32689 | B43: =VLOOKUP(A43,'NFIB SBO Core Index'!A:B,2,FALSE) -> 99.3714 | C43: =B43-B42 -> 2.0729 | D43: =B43-B31 -> -2.2826 | E43: 9170.977 | F43: =(E43-E31)/E31 -> 0.03748297
A44: ='NFIB SBO Core Index'!A44 -> 32720 | B44: =VLOOKUP(A44,'NFIB SBO Core Index'!A:B,2,FALSE) -> 99.5632 | C44: =B44-B43 -> 0.1918 | D44: =B44-B32 -> -0.5478
A45: ='NFIB SBO Core Index'!A45 -> 32751 | B45: =VLOOKUP(A45,'NFIB SBO Core Index'!A:B,2,FALSE) -> 99.6363 | C45: =B45-B44 -> 0.0731 | D45: =B45-B33 -> -2.0087
A46: ='NFIB SBO Core Index'!A46 -> 32781 | B46: =VLOOKUP(A46,'NFIB SBO Core Index'!A:B,2,FALSE) -> 101.873 | C46: =B46-B45 -> 2.2367 | D46: =B46-B34 -> 1.095 | E46: 9238.923 | F46: =(E46-E34)/E34 -> 0.039081206
A47: ='NFIB SBO Core Index'!A47 -> 32812 | B47: =VLOOKUP(A47,'NFIB SBO Core Index'!A:B,2,FALSE) -> 101.408 | C47: =B47-B46 -> -0.465 | D47: =B47-B35 -> -0.73
A48: ='NFIB SBO Core Index'!A48 -> 32842 | B48: =VLOOKUP(A48,'NFIB SBO Core Index'!A:B,2,FALSE) -> 99.7276 | C48: =B48-B47 -> -1.6804 | D48: =B48-B36 -> -2.1004
A49: ='NFIB SBO Core Index'!A49 -> 32873 | B49: =VLOOKUP(A49,'NFIB SBO Core Index'!A:B,2,FALSE) -> 100.303 | C49: =B49-B48 -> 0.5754 | D49: =B49-B37 -> -0.182 | E49: 9257.128 | F49: =(E49-E37)/E37 -> 0.027438112
A50: ='NFIB SBO Core Index'!A50 -> 32904 | B50: =VLOOKUP(A50,'NFIB SBO Core Index'!A:B,2,FALSE) -> 99.2801 | C50: =B50-B49 -> -1.0229 | D50: =B50-B38 -> -2.0089
A51: ='NFIB SBO Core Index'!A51 -> 32932 | B51: =VLOOKUP(A51,'NFIB SBO Core Index'!A:B,2,FALSE) -> 99.1523 | C51: =B51-B50 -> -0.1278 | D51: =B51-B39 -> -2.7397
A52: ='NFIB SBO Core Index'!A52 -> 32963 | B52: =VLOOKUP(A52,'NFIB SBO Core Index'!A:B,2,FALSE) -> 100.367 | C52: =B52-B51 -> 1.2147 | D52: =B52-B40 -> -1.004 | E52: 9358.289 | F52: =(E52-E40)/E40 -> 0.028213017
A53: ='NFIB SBO Core Index'!A53 -> 32993 | B53: =VLOOKUP(A53,'NFIB SBO Core Index'!A:B,2,FALSE) -> 99.2801 | C53: =B53-B52 -> -1.0869 | D53: =B53-B41 -> 1.2784
A54: ='NFIB SBO Core Index'!A54 -> 33024 | B54: =VLOOKUP(A54,'NFIB SBO Core Index'!A:B,2,FALSE) -> 99.3988 | C54: =B54-B53 -> 0.1187 | D54: =B54-B42 -> 2.1003
A55: ='NFIB SBO Core Index'!A55 -> 33054 | B55: =VLOOKUP(A55,'NFIB SBO Core Index'!A:B,2,FALSE) -> 98.7322 | C55: =B55-B54 -> -0.6666 | D55: =B55-B43 -> -0.6392 | E55: 9392.251 | F55: =(E55-E43)/E43 -> 0.024127637
A56: ='NFIB SBO Core Index'!A56 -> 33085 | B56: =VLOOKUP(A56,'NFIB SBO Core Index'!A:B,2,FALSE) -> 97.9195 | C56: =B56-B55 -> -0.8127 | D56: =B56-B44 -> -1.6437
A57: ='NFIB SBO Core Index'!A57 -> 33116 | B57: =VLOOKUP(A57,'NFIB SBO Core Index'!A:B,2,FALSE) -> 95.1617 | C57: =B57-B56 -> -2.7578 | D57: =B57-B45 -> -4.4746
A58: ='NFIB SBO Core Index'!A58 -> 33146 | B58: =VLOOKUP(A58,'NFIB SBO Core Index'!A:B,2,FALSE) -> 92.9244 | C58: =B58-B57 -> -2.2373 | D58: =B58-B46 -> -8.9486 | E58: 9398.499 | F58: =(E58-E46)/E46 -> 0.017272143
A59: ='NFIB SBO Core Index'!A59 -> 33177 | B59: =VLOOKUP(A59,'NFIB SBO Core Index'!A:B,2,FALSE) -> 91.6369 | C59: =B59-B58 -> -1.2875 | D59: =B59-B47 -> -9.7711
A60: ='NFIB SBO Core Index'!A60 -> 33207 | B60: =VLOOKUP(A60,'NFIB SBO Core Index'!A:B,2,FALSE) -> 91.783 | C60: =B60-B59 -> 0.1461 | D60: =B60-B48 -> -7.9446
A61: ='NFIB SBO Core Index'!A61 -> 33238 | B61: =VLOOKUP(A61,'NFIB SBO Core Index'!A:B,2,FALSE) -> 91.719 | C61: =B61-B60 -> -0.064 | D61: =B61-B49 -> -8.584 | E61: 9312.937 | F61: =(E61-E49)/E49 -> 0.0060287597
A62: ='NFIB SBO Core Index'!A62 -> 33269 | B62: =VLOOKUP(A62,'NFIB SBO Core Index'!A:B,2,FALSE) -> 91.2442 | C62: =B62-B61 -> -0.4748 | D62: =B62-B50 -> -8.0359
A63: ='NFIB SBO Core Index'!A63 -> 33297 | B63: =VLOOKUP(A63,'NFIB SBO Core Index'!A:B,2,FALSE) -> 95.4083 | C63: =B63-B62 -> 4.1641 | D63: =B63-B51 -> -3.744
A64: ='NFIB SBO Core Index'!A64 -> 33328 | B64: =VLOOKUP(A64,'NFIB SBO Core Index'!A:B,2,FALSE) -> 100.093 | C64: =B64-B63 -> 4.6847 | D64: =B64-B52 -> -0.274 | E64: 9269.367 | F64: =(E64-E52)/E52 -> -0.0095019506
A65: ='NFIB SBO Core Index'!A65 -> 33358 | B65: =VLOOKUP(A65,'NFIB SBO Core Index'!A:B,2,FALSE) -> 100.193 | C65: =B65-B64 -> 0.1 | D65: =B65-B53 -> 0.9129
A66: ='NFIB SBO Core Index'!A66 -> 33389 | B66: =VLOOKUP(A66,'NFIB SBO Core Index'!A:B,2,FALSE) -> 99.3988 | C66: =B66-B65 -> -0.7942 | D66: =B66-B54 -> 0
A67: ='NFIB SBO Core Index'!A67 -> 33419 | B67: =VLOOKUP(A67,'NFIB SBO Core Index'!A:B,2,FALSE) -> 99.5541 | C67: =B67-B66 -> 0.1553 | D67: =B67-B55 -> 0.8219 | E67: 9341.642 | F67: =(E67-E55)/E55 -> -0.0053883781
A68: ='NFIB SBO Core Index'!A68 -> 33450 | B68: =VLOOKUP(A68,'NFIB SBO Core Index'!A:B,2,FALSE) -> 100.568 | C68: =B68-B67 -> 1.0139 | D68: =B68-B56 -> 2.6485
A69: ='NFIB SBO Core Index'!A69 -> 33481 | B69: =VLOOKUP(A69,'NFIB SBO Core Index'!A:B,2,FALSE) -> 98.4491 | C69: =B69-B68 -> -2.1189 | D69: =B69-B57 -> 3.2874
A70: ='NFIB SBO Core Index'!A70 -> 33511 | B70: =VLOOKUP(A70,'NFIB SBO Core Index'!A:B,2,FALSE) -> 99.408 | C70: =B70-B69 -> 0.9589 | D70: =B70-B58 -> 6.4836 | E70: 9388.845 | F70: =(E70-E58)/E58 -> -0.0010271853
A71: ='NFIB SBO Core Index'!A71 -> 33542 | B71: =VLOOKUP(A71,'NFIB SBO Core Index'!A:B,2,FALSE) -> 97.8464 | C71: =B71-B70 -> -1.5616 | D71: =B71-B59 -> 6.2095
A72: ='NFIB SBO Core Index'!A72 -> 33572 | B72: =VLOOKUP(A72,'NFIB SBO Core Index'!A:B,2,FALSE) -> 95.253 | C72: =B72-B71 -> -2.5934 | D72: =B72-B60 -> 3.47
A73: ='NFIB SBO Core Index'!A73 -> 33603 | B73: =VLOOKUP(A73,'NFIB SBO Core Index'!A:B,2,FALSE) -> 95.8283 | C73: =B73-B72 -> 0.5753 | D73: =B73-B61 -> 4.1093 | E73: 9421.565 | F73: =(E73-E61)/E61 -> 0.011664204
A74: ='NFIB SBO Core Index'!A74 -> 33634 | B74: =VLOOKUP(A74,'NFIB SBO Core Index'!A:B,2,FALSE) -> 96.7232 | C74: =B74-B73 -> 0.8949 | D74: =B74-B62 -> 5.479
A75: ='NFIB SBO Core Index'!A75 -> 33663 | B75: =VLOOKUP(A75,'NFIB SBO Core Index'!A:B,2,FALSE) -> 98.4217 | C75: =B75-B74 -> 1.6985 | D75: =B75-B63 -> 3.0134
A76: ='NFIB SBO Core Index'!A76 -> 33694 | B76: =VLOOKUP(A76,'NFIB SBO Core Index'!A:B,2,FALSE) -> 100.093 | C76: =B76-B75 -> 1.6713 | D76: =B76-B64 -> 0 | E76: 9534.346 | F76: =(E76-E64)/E64 -> 0.028586526
A77: ='NFIB SBO Core Index'!A77 -> 33724 | B77: =VLOOKUP(A77,'NFIB SBO Core Index'!A:B,2,FALSE) -> 100.65 | C77: =B77-B76 -> 0.557 | D77: =B77-B65 -> 0.457
A78: ='NFIB SBO Core Index'!A78 -> 33755 | B78: =VLOOKUP(A78,'NFIB SBO Core Index'!A:B,2,FALSE) -> 100.769 | C78: =B78-B77 -> 0.119 | D78: =B78-B66 -> 1.3702
A79: ='NFIB SBO Core Index'!A79 -> 33785 | B79: =VLOOKUP(A79,'NFIB SBO Core Index'!A:B,2,FALSE) -> 101.198 | C79: =B79-B78 -> 0.429 | D79: =B79-B67 -> 1.6439 | E79: 9637.732 | F79: =(E79-E67)/E67 -> 0.031695713
A80: ='NFIB SBO Core Index'!A80 -> 33816 | B80: =VLOOKUP(A80,'NFIB SBO Core Index'!A:B,2,FALSE) -> 99.0153 | C80: =B80-B79 -> -2.1827 | D80: =B80-B68 -> -1.5527
A81: ='NFIB SBO Core Index'!A81 -> 33847 | B81: =VLOOKUP(A81,'NFIB SBO Core Index'!A:B,2,FALSE) -> 99.9102 | C81: =B81-B80 -> 0.8949 | D81: =B81-B69 -> 1.4611
A82: ='NFIB SBO Core Index'!A82 -> 33877 | B82: =VLOOKUP(A82,'NFIB SBO Core Index'!A:B,2,FALSE) -> 98.5861 | C82: =B82-B81 -> -1.3241 | D82: =B82-B70 -> -0.8219 | E82: 9732.979 | F82: =(E82-E70)/E70 -> 0.036653497
A83: ='NFIB SBO Core Index'!A83 -> 33908 | B83: =VLOOKUP(A83,'NFIB SBO Core Index'!A:B,2,FALSE) -> 98.0291 | C83: =B83-B82 -> -0.557 | D83: =B83-B71 -> 0.1827
A84: ='NFIB SBO Core Index'!A84 -> 33938 | B84: =VLOOKUP(A84,'NFIB SBO Core Index'!A:B,2,FALSE) -> 100.367 | C84: =B84-B83 -> 2.3379 | D84: =B84-B72 -> 5.114
A85: ='NFIB SBO Core Index'!A85 -> 33969 | B85: =VLOOKUP(A85,'NFIB SBO Core Index'!A:B,2,FALSE) -> 100.668 | C85: =B85-B84 -> 0.301 | D85: =B85-B73 -> 4.8397 | E85: 9834.51 | F85: =(E85-E73)/E73 -> 0.043829767
A86: ='NFIB SBO Core Index'!A86 -> 34000 | B86: =VLOOKUP(A86,'NFIB SBO Core Index'!A:B,2,FALSE) -> 100.65 | C86: =B86-B85 -> -0.018 | D86: =B86-B74 -> 3.9268
A87: ='NFIB SBO Core Index'!A87 -> 34028 | B87: =VLOOKUP(A87,'NFIB SBO Core Index'!A:B,2,FALSE) -> 98.3304 | C87: =B87-B86 -> -2.3196 | D87: =B87-B75 -> -0.0913
A88: ='NFIB SBO Core Index'!A88 -> 34059 | B88: =VLOOKUP(A88,'NFIB SBO Core Index'!A:B,2,FALSE) -> 97.4446 | C88: =B88-B87 -> -0.8858 | D88: =B88-B76 -> -2.6484 | E88: 9850.973 | F88: =(E88-E76)/E76 -> 0.033209095
A89: ='NFIB SBO Core Index'!A89 -> 34089 | B89: =VLOOKUP(A89,'NFIB SBO Core Index'!A:B,2,FALSE) -> 95.4448 | C89: =B89-B88 -> -1.9998 | D89: =B89-B77 -> -5.2052
A90: ='NFIB SBO Core Index'!A90 -> 34120 | B90: =VLOOKUP(A90,'NFIB SBO Core Index'!A:B,2,FALSE) -> 93.7372 | C90: =B90-B89 -> -1.7076 | D90: =B90-B78 -> -7.0318
A91: ='NFIB SBO Core Index'!A91 -> 34150 | B91: =VLOOKUP(A91,'NFIB SBO Core Index'!A:B,2,FALSE) -> 92.8879 | C91: =B91-B90 -> -0.8493 | D91: =B91-B79 -> -8.3101 | E91: 9908.347 | F91: =(E91-E79)/E79 -> 0.028078702
A92: ='NFIB SBO Core Index'!A92 -> 34181 | B92: =VLOOKUP(A92,'NFIB SBO Core Index'!A:B,2,FALSE) -> 93.8102 | C92: =B92-B91 -> 0.9223 | D92: =B92-B80 -> -5.2051
A93: ='NFIB SBO Core Index'!A93 -> 34212 | B93: =VLOOKUP(A93,'NFIB SBO Core Index'!A:B,2,FALSE) -> 92.4222 | C93: =B93-B92 -> -1.388 | D93: =B93-B81 -> -7.488
A94: ='NFIB SBO Core Index'!A94 -> 34242 | B94: =VLOOKUP(A94,'NFIB SBO Core Index'!A:B,2,FALSE) -> 94.1116 | C94: =B94-B93 -> 1.6894 | D94: =B94-B82 -> -4.4745 | E94: 9955.641 | F94: =(E94-E82)/E82 -> 0.022877066
A95: ='NFIB SBO Core Index'!A95 -> 34273 | B95: =VLOOKUP(A95,'NFIB SBO Core Index'!A:B,2,FALSE) -> 94.9243 | C95: =B95-B94 -> 0.8127 | D95: =B95-B83 -> -3.1048
A96: ='NFIB SBO Core Index'!A96 -> 34303 | B96: =VLOOKUP(A96,'NFIB SBO Core Index'!A:B,2,FALSE) -> 98.5404 | C96: =B96-B95 -> 3.6161 | D96: =B96-B84 -> -1.8266
A97: ='NFIB SBO Core Index'!A97 -> 34334 | B97: =VLOOKUP(A97,'NFIB SBO Core Index'!A:B,2,FALSE) -> 98.1113 | C97: =B97-B96 -> -0.4291 | D97: =B97-B85 -> -2.5567 | E97: 10091.049 | F97: =(E97-E85)/E85 -> 0.02608559
A98: ='NFIB SBO Core Index'!A98 -> 34365 | B98: =VLOOKUP(A98,'NFIB SBO Core Index'!A:B,2,FALSE) -> 99.6454 | C98: =B98-B97 -> 1.5341 | D98: =B98-B86 -> -1.0046
A99: ='NFIB SBO Core Index'!A99 -> 34393 | B99: =VLOOKUP(A99,'NFIB SBO Core Index'!A:B,2,FALSE) -> 99.8828 | C99: =B99-B98 -> 0.2374 | D99: =B99-B87 -> 1.5524
A100: ='NFIB SBO Core Index'!A100 -> 34424 | B100: =VLOOKUP(A100,'NFIB SBO Core Index'!A:B,2,FALSE) -> 100.093 | C100: =B100-B99 -> 0.2102 | D100: =B100-B88 -> 2.6484 | E100: 10188.954 | F100: =(E100-E88)/E88 -> 0.034309403
...

Sheet SBO_vs_SP500
A1: Date | B1: Small Business Optimism Index | C1: Small Business Optimism Index MoM | D1: Small Business Optimism Index YoY | E1: S&P 500 Index | F1: S&P 500 Index YoY %
A2: 31443 | B2: =VLOOKUP(A2,'NFIB SBO Core Index'!A:B,2,FALSE) -> 100.285 | E2: 211.78
A3: 31471 | B3: =VLOOKUP(A3,'NFIB SBO Core Index'!A:B,2,FALSE) -> 99.7915 | C3: =B3-B2 -> -0.4935 | E3: 226.92
A4: 31502 | B4: =VLOOKUP(A4,'NFIB SBO Core Index'!A:B,2,FALSE) -> 101.463 | C4: =B4-B3 -> 1.6715 | E4: 238.89999
A5: 31532 | B5: =VLOOKUP(A5,'NFIB SBO Core Index'!A:B,2,FALSE) -> 101.015 | C5: =B5-B4 -> -0.448 | E5: 235.52
A6: 31563 | B6: =VLOOKUP(A6,'NFIB SBO Core Index'!A:B,2,FALSE) -> 101.956 | C6: =B6-B5 -> 0.941 | E6: 247.35001
A7: 31593 | B7: =VLOOKUP(A7,'NFIB SBO Core Index'!A:B,2,FALSE) -> 101.289 | C7: =B7-B6 -> -0.667 | E7: 250.84
A8: 31624 | B8: =VLOOKUP(A8,'NFIB SBO Core Index'!A:B,2,FALSE) -> 99.8372 | C8: =B8-B7 -> -1.4518 | E8: 236.11999
A9: 31655 | B9: =VLOOKUP(A9,'NFIB SBO Core Index'!A:B,2,FALSE) -> 98.8144 | C9: =B9-B8 -> -1.0228 | E9: 252.92999
A10: 31685 | B10: =VLOOKUP(A10,'NFIB SBO Core Index'!A:B,2,FALSE) -> 98.5861 | C10: =B10-B9 -> -0.2283 | E10: 231.32001
A11: 31716 | B11: =VLOOKUP(A11,'NFIB SBO Core Index'!A:B,2,FALSE) -> 98.7596 | C11: =B11-B10 -> 0.1735 | E11: 243.98
A12: 31746 | B12: =VLOOKUP(A12,'NFIB SBO Core Index'!A:B,2,FALSE) -> 97.536 | C12: =B12-B11 -> -1.2236 | E12: 249.22
A13: 31777 | B13: =VLOOKUP(A13,'NFIB SBO Core Index'!A:B,2,FALSE) -> 100.668 | C13: =B13-B12 -> 3.132 | E13: 242.17
A14: 31808 | B14: =VLOOKUP(A14,'NFIB SBO Core Index'!A:B,2,FALSE) -> 100.102 | C14: =B14-B13 -> -0.566 | D14: =B14-B2 -> -0.183 | E14: 274.07999 | F14: =(E14-E2)/E2 -> 0.29417314
A15: 31836 | B15: =VLOOKUP(A15,'NFIB SBO Core Index'!A:B,2,FALSE) -> 100.613 | C15: =B15-B14 -> 0.511 | D15: =B15-B3 -> 0.8215 | E15: 284.20001 | F15: =(E15-E3)/E3 -> 0.25242383
A16: 31867 | B16: =VLOOKUP(A16,'NFIB SBO Core Index'!A:B,2,FALSE) -> 101.189 | C16: =B16-B15 -> 0.576 | D16: =B16-B4 -> -0.274 | E16: 291.70001 | F16: =(E16-E4)/E4 -> 0.22101306
A17: 31897 | B17: =VLOOKUP(A17,'NFIB SBO Core Index'!A:B,2,FALSE) -> 100.102 | C17: =B17-B16 -> -1.087 | D17: =B17-B5 -> -0.913 | E17: 288.35998 | F17: =(E17-E5)/E5 -> 0.22435454
A18: 31928 | B18: =VLOOKUP(A18,'NFIB SBO Core Index'!A:B,2,FALSE) -> 99.8554 | C18: =B18-B17 -> -0.2466 | D18: =B18-B6 -> -2.1006 | E18: 290.10001 | F18: =(E18-E6)/E6 -> 0.17283202
A19: 31958 | B19: =VLOOKUP(A19,'NFIB SBO Core Index'!A:B,2,FALSE) -> 101.746 | C19: =B19-B18 -> 1.8906 | D19: =B19-B7 -> 0.457 | E19: 304 | F19: =(E19-E7)/E7 -> 0.21192794
A20: 31989 | B20: =VLOOKUP(A20,'NFIB SBO Core Index'!A:B,2,FALSE) -> 102.485 | C20: =B20-B19 -> 0.739 | D20: =B20-B8 -> 2.6478 | E20: 318.66 | F20: =(E20-E8)/E8 -> 0.34956806
A21: 32020 | B21: =VLOOKUP(A21,'NFIB SBO Core Index'!A:B,2,FALSE) -> 103.745 | C21: =B21-B20 -> 1.26 | D21: =B21-B9 -> 4.9306 | E21: 329.79999 | F21: =(E21-E9)/E9 -> 0.30391807
A22: 32050 | B22: =VLOOKUP(A22,'NFIB SBO Core Index'!A:B,2,FALSE) -> 102.421 | C22: =B22-B21 -> -1.324 | D22: =B22-B10 -> 3.8349 | E22: 321.82999 | F22: =(E22-E10)/E10 -> 0.39127606
A23: 32081 | B23: =VLOOKUP(A23,'NFIB SBO Core Index'!A:B,2,FALSE) -> 101.59 | C23: =B23-B22 -> -0.831 | D23: =B23-B11 -> 2.8304 | E23: 251.78999 | F23: =(E23-E11)/E11 -> 0.032010809
A24: 32111 | B24: =VLOOKUP(A24,'NFIB SBO Core Index'!A:B,2,FALSE) -> 98.6318 | C24: =B24-B23 -> -2.9582 | D24: =B24-B12 -> 1.0958 | E24: 230.3 | F24: =(E24-E12)/E12 -> -0.075916852
A25: 32142 | B25: =VLOOKUP(A25,'NFIB SBO Core Index'!A:B,2,FALSE) -> 100.029 | C25: =B25-B24 -> 1.3972 | D25: =B25-B13 -> -0.639 | E25: 247.08 | F25: =(E25-E13)/E13 -> 0.02027503
... A421: 44196 | B421: =VLOOKUP(A421,'NFIB SBO Core Index'!A:B,2,FALSE) -> 95.708 | C421: =B421-B420 -> -5.479 | D421: =B421-B409 -> -6.575 | E421: 3756.0701 | F421: =(E421-E409)/E409 -> 0.16258923

Sheet SBO_Leading_vs_GDP
A1: Date | B1: SBO - Leading Index | C1: SBO - Leading Index MoM | D1: SBO - Leading Index YoY | E1: US Real GDP, Billions 2012 USD, Seasonally Adjusted | F1: GDP YoY %
A2: ='NFIB SBO Core Index'!A2 -> 31443 | B2: =AVERAGE('Expansion Plans'!B2+'Employment Plans'!B2+'Inventory Plans'!B2+'Economic Expectations'!B2+'Real Sales Expectations'!B2) -> 57
A3: ='NFIB SBO Core Index'!A3 -> 31471 | B3: =AVERAGE('Expansion Plans'!B3+'Employment Plans'!B3+'Inventory Plans'!B3+'Economic Expectations'!B3+'Real Sales Expectations'!B3) -> 56 | C3: =B3-B2 -> -1
A4: ='NFIB SBO Core Index'!A4 -> 31502 | B4: =AVERAGE('Expansion Plans'!B4+'Employment Plans'!B4+'Inventory Plans'!B4+'Economic Expectations'!B4+'Real Sales Expectations'!B4) -> 78 | C4: =B4-B3 -> 22 | E4: 8148.603
A5: ='NFIB SBO Core Index'!A5 -> 31532 | B5: =AVERAGE('Expansion Plans'!B5+'Employment Plans'!B5+'Inventory Plans'!B5+'Economic Expectations'!B5+'Real Sales Expectations'!B5) -> 70 | C5: =B5-B4 -> -8
A6: ='NFIB SBO Core Index'!A6 -> 31563 | B6: =AVERAGE('Expansion Plans'!B6+'Employment Plans'!B6+'Inventory Plans'!B6+'Economic Expectations'!B6+'Real Sales Expectations'!B6) -> 67 | C6: =B6-B5 -> -3
A7: ='NFIB SBO Core Index'!A7 -> 31593 | B7: =AVERAGE('Expansion Plans'!B7+'Employment Plans'!B7+'Inventory Plans'!B7+'Economic Expectations'!B7+'Real Sales Expectations'!B7) -> 71 | C7: =B7-B6 -> 4 | E7: 8185.303
A8: ='NFIB SBO Core Index'!A8 -> 31624 | B8: =AVERAGE('Expansion Plans'!B8+'Employment Plans'!B8+'Inventory Plans'!B8+'Economic Expectations'!B8+'Real Sales Expectations'!B8) -> 50 | C8: =B8-B7 -> -21
A9: ='NFIB SBO Core Index'!A9 -> 31655 | B9: =AVERAGE('Expansion Plans'!B9+'Employment Plans'!B9+'Inventory Plans'!B9+'Economic Expectations'!B9+'Real Sales Expectations'!B9) -> 39 | C9: =B9-B8 -> -11
A10: ='NFIB SBO Core Index'!A10 -> 31685 | B10: =AVERAGE('Expansion Plans'!B10+'Employment Plans'!B10+'Inventory Plans'!B10+'Economic Expectations'!B10+'Real Sales Expectations'!B10) -> 36 | C10: =B10-B9 -> -3 | E10: 8263.639
A11: ='NFIB SBO Core Index'!A11 -> 31716 | B11: =AVERAGE('Expansion Plans'!B11+'Employment Plans'!B11+'Inventory Plans'!B11+'Economic Expectations'!B11+'Real Sales Expectations'!B11) -> 43 | C11: =B11-B10 -> 7
A12: ='NFIB SBO Core Index'!A12 -> 31746 | B12: =AVERAGE('Expansion Plans'!B12+'Employment Plans'!B12+'Inventory Plans'!B12+'Economic Expectations'!B12+'Real Sales Expectations'!B12) -> 27 | C12: =B12-B11 -> -16
A13: ='NFIB SBO Core Index'!A13 -> 31777 | B13: =AVERAGE('Expansion Plans'!B13+'Employment Plans'!B13+'Inventory Plans'!B13+'Economic Expectations'!B13+'Real Sales Expectations'!B13) -> 42 | C13: =B13-B12 -> 15 | E13: 8308.021
A14: ='NFIB SBO Core Index'!A14 -> 31808 | B14: =AVERAGE('Expansion Plans'!B14+'Employment Plans'!B14+'Inventory Plans'!B14+'Economic Expectations'!B14+'Real Sales Expectations'!B14) -> 46 | C14: =B14-B13 -> 4 | D14: =B14-B2 -> -11
A15: ='NFIB SBO Core Index'!A15 -> 31836 | B15: =AVERAGE('Expansion Plans'!B15+'Employment Plans'!B15+'Inventory Plans'!B15+'Economic Expectations'!B15+'Real Sales Expectations'!B15) -> 54 | C15: =B15-B14 -> 8 | D15: =B15-B3 -> -2
A16: ='NFIB SBO Core Index'!A16 -> 31867 | B16: =AVERAGE('Expansion Plans'!B16+'Employment Plans'!B16+'Inventory Plans'!B16+'Economic Expectations'!B16+'Real Sales Expectations'!B16) -> 54 | C16: =B16-B15 -> 0 | D16: =B16-B4 -> -24 | E16: 8369.93 | F16: =(E16-E4)/E4 -> 0.027161343
A17: ='NFIB SBO Core Index'!A17 -> 31897 | B17: =AVERAGE('Expansion Plans'!B17+'Employment Plans'!B17+'Inventory Plans'!B17+'Economic Expectations'!B17+'Real Sales Expectations'!B17) -> 45 | C17: =B17-B16 -> -9 | D17: =B17-B5 -> -25
A18: ='NFIB SBO Core Index'!A18 -> 31928 | B18: =AVERAGE('Expansion Plans'!B18+'Employment Plans'!B18+'Inventory Plans'!B18+'Economic Expectations'!B18+'Real Sales Expectations'!B18) -> 35 | C18: =B18-B17 -> -10 | D18: =B18-B6 -> -32
A19: ='NFIB SBO Core Index'!A19 -> 31958 | B19: =AVERAGE('Expansion Plans'!B19+'Employment Plans'!B19+'Inventory Plans'!B19+'Economic Expectations'!B19+'Real Sales Expectations'!B19) -> 54 | C19: =B19-B18 -> 19 | D19: =B19-B7 -> -17 | E19: 8460.233 | F19: =(E19-E7)/E7 -> 0.03358825
A20: ='NFIB SBO Core Index'!A20 -> 31989 | B20: =AVERAGE('Expansion Plans'!B20+'Employment Plans'!B20+'Inventory Plans'!B20+'Economic Expectations'!B20+'Real Sales Expectations'!B20) -> 54 | C20: =B20-B19 -> 0 | D20: =B20-B8 -> 4
A21: ='NFIB SBO Core Index'!A21 -> 32020 | B21: =AVERAGE('Expansion Plans'!B21+'Employment Plans'!B21+'Inventory Plans'!B21+'Economic Expectations'!B21+'Real Sales Expectations'!B21) -> 75 | C21: =B21-B20 -> 21 | D21: =B21-B9 -> 36
A22: ='NFIB SBO Core Index'!A22 -> 32050 | B22: =AVERAGE('Expansion Plans'!B22+'Employment Plans'!B22+'Inventory Plans'!B22+'Economic Expectations'!B22+'Real Sales Expectations'!B22) -> 57 | C22: =B22-B21 -> -18 | D22: =B22-B10 -> 21 | E22: 8533.635 | F22: =(E22-E10)/E10 -> 0.032672773
A23: ='NFIB SBO Core Index'!A23 -> 32081 | B23: =AVERAGE('Expansion Plans'!B23+'Employment Plans'!B23+'Inventory Plans'!B23+'Economic Expectations'!B23+'Real Sales Expectations'!B23) -> 52 | C23: =B23-B22 -> -5 | D23: =B23-B11 -> 9
A24: ='NFIB SBO Core Index'!A24 -> 32111 | B24: =AVERAGE('Expansion Plans'!B24+'Employment Plans'!B24+'Inventory Plans'!B24+'Economic Expectations'!B24+'Real Sales Expectations'!B24) -> 26 | C24: =B24-B23 -> -26 | D24: =B24-B12 -> -1
A25: ='NFIB SBO Core Index'!A25 -> 32142 | B25: =AVERAGE('Expansion Plans'!B25+'Employment Plans'!B25+'Inventory Plans'!B25+'Economic Expectations'!B25+'Real Sales Expectations'!B25) -> 24 | C25: =B25-B24 -> -2 | D25: =B25-B13 -> -18 | E25: 8680.162 | F25: =(E25-E13)/E13 -> 0.044792978
A26: ='NFIB SBO Core Index'!A26 -> 32173 | B26: =AVERAGE('Expansion Plans'!B26+'Employment Plans'!B26+'Inventory Plans'!B26+'Economic Expectations'!B26+'Real Sales Expectations'!B26) -> 35 | C26: =B26-B25 -> 11 | D26: =B26-B14 -> -11
A27: ='NFIB SBO Core Index'!A27 -> 32202 | B27: =AVERAGE('Expansion Plans'!B27+'Employment Plans'!B27+'Inventory Plans'!B27+'Economic Expectations'!B27+'Real Sales Expectations'!B27) -> 28 | C27: =B27-B26 -> -7 | D27: =B27-B15 -> -26
A28: ='NFIB SBO Core Index'!A28 -> 32233 | B28: =AVERAGE('Expansion Plans'!B28+'Employment Plans'!B28+'Inventory Plans'!B28+'Economic Expectations'!B28+'Real Sales Expectations'!B28) -> 52 | C28: =B28-B27 -> 24 | D28: =B28-B16 -> -2 | E28: 8725.006 | F28: =(E28-E16)/E16 -> 0.042422816
A29: ='NFIB SBO Core Index'!A29 -> 32263 | B29: =AVERAGE('Expansion Plans'!B29+'Employment Plans'!B29+'Inventory Plans'!B29+'Economic Expectations'!B29+'Real Sales Expectations'!B29) -> 47 | C29: =B29-B28 -> -5 | D29: =B29-B17 -> 2
A30: ='NFIB SBO Core Index'!A30 -> 32294 | B30: =AVERAGE('Expansion Plans'!B30+'Employment Plans'!B30+'Inventory Plans'!B30+'Economic Expectations'!B30+'Real Sales Expectations'!B30) -> 33 | C30: =B30-B29 -> -14 | D30: =B30-B18 -> -2
A31: ='NFIB SBO Core Index'!A31 -> 32324 | B31: =AVERAGE('Expansion Plans'!B31+'Employment Plans'!B31+'Inventory Plans'!B31+'Economic Expectations'!B31+'Real Sales Expectations'!B31) -> 46 | C31: =B31-B30 -> 13 | D31: =B31-B19 -> -8 | E31: 8839.641 | F31: =(E31-E19)/E19 -> 0.044846046
A32: ='NFIB SBO Core Index'!A32 -> 32355 | B32: =AVERAGE('Expansion Plans'!B32+'Employment Plans'!B32+'Inventory Plans'!B32+'Economic Expectations'!B32+'Real Sales Expectations'!B32) -> 34 | C32: =B32-B31 -> -12 | D32: =B32-B20 -> -20
A33: ='NFIB SBO Core Index'!A33 -> 32386 | B33: =AVERAGE('Expansion Plans'!B33+'Employment Plans'!B33+'Inventory Plans'!B33+'Economic Expectations'!B33+'Real Sales Expectations'!B33) -> 50 | C33: =B33-B32 -> 16 | D33: =B33-B21 -> -25
A34: ='NFIB SBO Core Index'!A34 -> 32416 | B34: =AVERAGE('Expansion Plans'!B34+'Employment Plans'!B34+'Inventory Plans'!B34+'Economic Expectations'!B34+'Real Sales Expectations'!B34) -> 41 | C34: =B34-B33 -> -9 | D34: =B34-B22 -> -16 | E34: 8891.435 | F34: =(E34-E22)/E22 -> 0.041928205
A35: ='NFIB SBO Core Index'!A35 -> 32447 | B35: =AVERAGE('Expansion Plans'!B35+'Employment Plans'!B35+'Inventory Plans'!B35+'Economic Expectations'!B35+'Real Sales Expectations'!B35) -> 52 | C35: =B35-B34 -> 11 | D35: =B35-B23 -> 0
A36: ='NFIB SBO Core Index'!A36 -> 32477 | B36: =AVERAGE('Expansion Plans'!B36+'Employment Plans'!B36+'Inventory Plans'!B36+'Economic Expectations'!B36+'Real Sales Expectations'!B36) -> 47 | C36: =B36-B35 -> -5 | D36: =B36-B24 -> 21
A37: ='NFIB SBO Core Index'!A37 -> 32508 | B37: =AVERAGE('Expansion Plans'!B37+'Employment Plans'!B37+'Inventory Plans'!B37+'Economic Expectations'!B37+'Real Sales Expectations'!B37) -> 39 | C37: =B37-B36 -> -8 | D37: =B37-B25 -> 15 | E37: 9009.913 | F37: =(E37-E25)/E25 -> 0.037989038
A38: ='NFIB SBO Core Index'!A38 -> 32539 | B38: =AVERAGE('Expansion Plans'!B38+'Employment Plans'!B38+'Inventory Plans'!B38+'Economic Expectations'!B38+'Real Sales Expectations'!B38) -> 42 | C38: =B38-B37 -> 3 | D38: =B38-B26 -> 7
A39: ='NFIB SBO Core Index'!A39 -> 32567 | B39: =AVERAGE('Expansion Plans'!B39+'Employment Plans'!B39+'Inventory Plans'!B39+'Economic Expectations'!B39+'Real Sales Expectations'!B39) -> 53 | C39: =B39-B38 -> 11 | D39: =B39-B27 -> 25
A40: ='NFIB SBO Core Index'!A40 -> 32598 | B40: =AVERAGE('Expansion Plans'!B40+'Employment Plans'!B40+'Inventory Plans'!B40+'Economic Expectations'!B40+'Real Sales Expectations'!B40) -> 40 | C40: =B40-B39 -> -13 | D40: =B40-B28 -> -12 | E40: 9101.508 | F40: =(E40-E28)/E28 -> 0.043152062
A41: ='NFIB SBO Core Index'!A41 -> 32628 | B41: =AVERAGE('Expansion Plans'!B41+'Employment Plans'!B41+'Inventory Plans'!B41+'Economic Expectations'!B41+'Real Sales Expectations'!B41) -> 19 | C41: =B41-B40 -> -21 | D41: =B41-B29 -> -28
A42: ='NFIB SBO Core Index'!A42 -> 32659 | B42: =AVERAGE('Expansion Plans'!B42+'Employment Plans'!B42+'Inventory Plans'!B42+'Economic Expectations'!B42+'Real Sales Expectations'!B42) -> 13 | C42: =B42-B41 -> -6 | D42: =B42-B30 -> -20
A43: ='NFIB SBO Core Index'!A43 -> 32689 | B43: =AVERAGE('Expansion Plans'!B43+'Employment Plans'!B43+'Inventory Plans'!B43+'Economic Expectations'!B43+'Real Sales Expectations'!B43) -> 30 | C43: =B43-B42 -> 17 | D43: =B43-B31 -> -16 | E43: 9170.977 | F43: =(E43-E31)/E31 -> 0.03748297
A44: ='NFIB SBO Core Index'!A44 -> 32720 | B44: =AVERAGE('Expansion Plans'!B44+'Employment Plans'!B44+'Inventory Plans'!B44+'Economic Expectations'!B44+'Real Sales Expectations'!B44) -> 25 | C44: =B44-B43 -> -5 | D44: =B44-B32 -> -9
A45: ='NFIB SBO Core Index'!A45 -> 32751 | B45: =AVERAGE('Expansion Plans'!B45+'Employment Plans'!B45+'Inventory Plans'!B45+'Economic Expectations'!B45+'Real Sales Expectations'!B45) -> 41 | C45: =B45-B44 -> 16 | D45: =B45-B33 -> -9
A46: ='NFIB SBO Core Index'!A46 -> 32781 | B46: =AVERAGE('Expansion Plans'!B46+'Employment Plans'!B46+'Inventory Plans'!B46+'Economic Expectations'!B46+'Real Sales Expectations'!B46) -> 58 | C46: =B46-B45 -> 17 | D46: =B46-B34 -> 17 | E46: 9238.923 | F46: =(E46-E34)/E34 -> 0.039081206
A47: ='NFIB SBO Core Index'!A47 -> 32812 | B47: =AVERAGE('Expansion Plans'!B47+'Employment Plans'!B47+'Inventory Plans'!B47+'Economic Expectations'!B47+'Real Sales Expectations'!B47) -> 56 | C47: =B47-B46 -> -2 | D47: =B47-B35 -> 4
A48: ='NFIB SBO Core Index'!A48 -> 32842 | B48: =AVERAGE('Expansion Plans'!B48+'Employment Plans'!B48+'Inventory Plans'!B48+'Economic Expectations'!B48+'Real Sales Expectations'!B48) -> 36 | C48: =B48-B47 -> -20 | D48: =B48-B36 -> -11
A49: ='NFIB SBO Core Index'!A49 -> 32873 | B49: =AVERAGE('Expansion Plans'!B49+'Employment Plans'!B49+'Inventory Plans'!B49+'Economic Expectations'!B49+'Real Sales Expectations'!B49) -> 40 | C49: =B49-B48 -> 4 | D49: =B49-B37 -> 1 | E49: 9257.128 | F49: =(E49-E37)/E37 -> 0.027438112
A50: ='NFIB SBO Core Index'!A50 -> 32904 | B50: =AVERAGE('Expansion Plans'!B50+'Employment Plans'!B50+'Inventory Plans'!B50+'Economic Expectations'!B50+'Real Sales Expectations'!B50) -> 35 | C50: =B50-B49 -> -5 | D50: =B50-B38 -> -7
A51: ='NFIB SBO Core Index'!A51 -> 32932 | B51: =AVERAGE('Expansion Plans'!B51+'Employment Plans'!B51+'Inventory Plans'!B51+'Economic Expectations'!B51+'Real Sales Expectations'!B51) -> 35 | C51: =B51-B50 -> 0 | D51: =B51-B39 -> -18
A52: ='NFIB SBO Core Index'!A52 -> 32963 | B52: =AVERAGE('Expansion Plans'!B52+'Employment Plans'!B52+'Inventory Plans'!B52+'Economic Expectations'!B52+'Real Sales Expectations'!B52) -> 41 | C52: =B52-B51 -> 6 | D52: =B52-B40 -> 1 | E52: 9358.289 | F52: =(E52-E40)/E40 -> 0.028213017
A53: ='NFIB SBO Core Index'!A53 -> 32993 | B53: =AVERAGE('Expansion Plans'!B53+'Employment Plans'!B53+'Inventory Plans'!B53+'Economic Expectations'!B53+'Real Sales Expectations'!B53) -> 37 | C53: =B53-B52 -> -4 | D53: =B53-B41 -> 18
A54: ='NFIB SBO Core Index'!A54 -> 33024 | B54: =AVERAGE('Expansion Plans'!B54+'Employment Plans'!B54+'Inventory Plans'!B54+'Economic Expectations'!B54+'Real Sales Expectations'!B54) -> 34 | C54: =B54-B53 -> -3 | D54: =B54-B42 -> 21
A55: ='NFIB SBO Core Index'!A55 -> 33054 | B55: =AVERAGE('Expansion Plans'!B55+'Employment Plans'!B55+'Inventory Plans'!B55+'Economic Expectations'!B55+'Real Sales Expectations'!B55) -> 32 | C55: =B55-B54 -> -2 | D55: =B55-B43 -> 2 | E55: 9392.251 | F55: =(E55-E43)/E43 -> 0.024127637
A56: ='NFIB SBO Core Index'!A56 -> 33085 | B56: =AVERAGE('Expansion Plans'!B56+'Employment Plans'!B56+'Inventory Plans'!B56+'Economic Expectations'!B56+'Real Sales Expectations'!B56) -> 27 | C56: =B56-B55 -> -5 | D56: =B56-B44 -> 2
A57: ='NFIB SBO Core Index'!A57 -> 33116 | B57: =AVERAGE('Expansion Plans'!B57+'Employment Plans'!B57+'Inventory Plans'!B57+'Economic Expectations'!B57+'Real Sales Expectations'!B57) -> -11 | C57: =B57-B56 -> -38 | D57: =B57-B45 -> -52
A58: ='NFIB SBO Core Index'!A58 -> 33146 | B58: =AVERAGE('Expansion Plans'!B58+'Employment Plans'!B58+'Inventory Plans'!B58+'Economic Expectations'!B58+'Real Sales Expectations'!B58) -> -20 | C58: =B58-B57 -> -9 | D58: =B58-B46 -> -78 | E58: 9398.499 | F58: =(E58-E46)/E46 -> 0.017272143
A59: ='NFIB SBO Core Index'!A59 -> 33177 | B59: =AVERAGE('Expansion Plans'!B59+'Employment Plans'!B59+'Inventory Plans'!B59+'Economic Expectations'!B59+'Real Sales Expectations'!B59) -> -42 | C59: =B59-B58 -> -22 | D59: =B59-B47 -> -98
A60: ='NFIB SBO Core Index'!A60 -> 33207 | B60: =AVERAGE('Expansion Plans'!B60+'Employment Plans'!B60+'Inventory Plans'!B60+'Economic Expectations'!B60+'Real Sales Expectations'!B60) -> -33 | C60: =B60-B59 -> 9 | D60: =B60-B48 -> -69
A61: ='NFIB SBO Core Index'!A61 -> 33238 | B61: =AVERAGE('Expansion Plans'!B61+'Employment Plans'!B61+'Inventory Plans'!B61+'Economic Expectations'!B61+'Real Sales Expectations'!B61) -> -10 | C61: =B61-B60 -> 23 | D61: =B61-B49 -> -50 | E61: 9312.937 | F61: =(E61-E49)/E49 -> 0.0060287597
A62: ='NFIB SBO Core Index'!A62 -> 33269 | B62: =AVERAGE('Expansion Plans'!B62+'Employment Plans'!B62+'Inventory Plans'!B62+'Economic Expectations'!B62+'Real Sales Expectations'!B62) -> -3 | C62: =B62-B61 -> 7 | D62: =B62-B50 -> -38
A63: ='NFIB SBO Core Index'!A63 -> 33297 | B63: =AVERAGE('Expansion Plans'!B63+'Employment Plans'!B63+'Inventory Plans'!B63+'Economic Expectations'!B63+'Real Sales Expectations'!B63) -> 60 | C63: =B63-B62 -> 63 | D63: =B63-B51 -> 25
A64: ='NFIB SBO Core Index'!A64 -> 33328 | B64: =AVERAGE('Expansion Plans'!B64+'Employment Plans'!B64+'Inventory Plans'!B64+'Economic Expectations'!B64+'Real Sales Expectations'!B64) -> 105 | C64: =B64-B63 -> 45 | D64: =B64-B52 -> 64 | E64: 9269.367 | F64: =(E64-E52)/E52 -> -0.0095019506
A65: ='NFIB SBO Core Index'!A65 -> 33358 | B65: =AVERAGE('Expansion Plans'!B65+'Employment Plans'!B65+'Inventory Plans'!B65+'Economic Expectations'!B65+'Real Sales Expectations'!B65) -> 103 | C65: =B65-B64 -> -2 | D65: =B65-B53 -> 66
A66: ='NFIB SBO Core Index'!A66 -> 33389 | B66: =AVERAGE('Expansion Plans'!B66+'Employment Plans'!B66+'Inventory Plans'!B66+'Economic Expectations'!B66+'Real Sales Expectations'!B66) -> 95 | C66: =B66-B65 -> -8 | D66: =B66-B54 -> 61
A67: ='NFIB SBO Core Index'!A67 -> 33419 | B67: =AVERAGE('Expansion Plans'!B67+'Employment Plans'!B67+'Inventory Plans'!B67+'Economic Expectations'!B67+'Real Sales Expectations'!B67) -> 97 | C67: =B67-B66 -> 2 | D67: =B67-B55 -> 65 | E67: 9341.642 | F67: =(E67-E55)/E55 -> -0.0053883781
A68: ='NFIB SBO Core Index'!A68 -> 33450 | B68: =AVERAGE('Expansion Plans'!B68+'Employment Plans'!B68+'Inventory Plans'!B68+'Economic Expectations'!B68+'Real Sales Expectations'!B68) -> 98 | C68: =B68-B67 -> 1 | D68: =B68-B56 -> 71
A69: ='NFIB SBO Core Index'!A69 -> 33481 | B69: =AVERAGE('Expansion Plans'!B69+'Employment Plans'!B69+'Inventory Plans'!B69+'Economic Expectations'!B69+'Real Sales Expectations'!B69) -> 86 | C69: =B69-B68 -> -12 | D69: =B69-B57 -> 97
A70: ='NFIB SBO Core Index'!A70 -> 33511 | B70: =AVERAGE('Expansion Plans'!B70+'Employment Plans'!B70+'Inventory Plans'!B70+'Economic Expectations'!B70+'Real Sales Expectations'!B70) -> 80 | C70: =B70-B69 -> -6 | D70: =B70-B58 -> 100 | E70: 9388.845 | F70: =(E70-E58)/E58 -> -0.0010271853
A71: ='NFIB SBO Core Index'!A71 -> 33542 | B71: =AVERAGE('Expansion Plans'!B71+'Employment Plans'!B71+'Inventory Plans'!B71+'Economic Expectations'!B71+'Real Sales Expectations'!B71) -> 72 | C71: =B71-B70 -> -8 | D71: =B71-B59 -> 114
A72: ='NFIB SBO Core Index'!A72 -> 33572 | B72: =AVERAGE('Expansion Plans'!B72+'Employment Plans'!B72+'Inventory Plans'!B72+'Economic Expectations'!B72+'Real Sales Expectations'!B72) -> 46 | C72: =B72-B71 -> -26 | D72: =B72-B60 -> 79
A73: ='NFIB SBO Core Index'!A73 -> 33603 | B73: =AVERAGE('Expansion Plans'!B73+'Employment Plans'!B73+'Inventory Plans'!B73+'Economic Expectations'!B73+'Real Sales Expectations'!B73) -> 51 | C73: =B73-B72 -> 5 | D73: =B73-B61 -> 61 | E73: 9421.565 | F73: =(E73-E61)/E61 -> 0.011664204
A74: ='NFIB SBO Core Index'!A74 -> 33634 | B74: =AVERAGE('Expansion Plans'!B74+'Employment Plans'!B74+'Inventory Plans'!B74+'Economic Expectations'!B74+'Real Sales Expectations'!B74) -> 66 | C74: =B74-B73 -> 15 | D74: =B74-B62 -> 69
A75: ='NFIB SBO Core Index'!A75 -> 33663 | B75: =AVERAGE('Expansion Plans'!B75+'Employment Plans'!B75+'Inventory Plans'!B75+'Economic Expectations'!B75+'Real Sales Expectations'!B75) -> 78 | C75: =B75-B74 -> 12 | D75: =B75-B63 -> 18
A76: ='NFIB SBO Core Index'!A76 -> 33694 | B76: =AVERAGE('Expansion Plans'!B76+'Employment Plans'!B76+'Inventory Plans'!B76+'Economic Expectations'!B76+'Real Sales Expectations'!B76) -> 98 | C76: =B76-B75 -> 20 | D76: =B76-B64 -> -7 | E76: 9534.346 | F76: =(E76-E64)/E64 -> 0.028586526
A77: ='NFIB SBO Core Index'!A77 -> 33724 | B77: =AVERAGE('Expansion Plans'!B77+'Employment Plans'!B77+'Inventory Plans'!B77+'Economic Expectations'!B77+'Real Sales Expectations'!B77) -> 99 | C77: =B77-B76 -> 1 | D77: =B77-B65 -> -4
A78: ='NFIB SBO Core Index'!A78 -> 33755 | B78: =AVERAGE('Expansion Plans'!B78+'Employment Plans'!B78+'Inventory Plans'!B78+'Economic Expectations'!B78+'Real Sales Expectations'!B78) -> 95 | C78: =B78-B77 -> -4 | D78: =B78-B66 -> 0
A79: ='NFIB SBO Core Index'!A79 -> 33785 | B79: =AVERAGE('Expansion Plans'!B79+'Employment Plans'!B79+'Inventory Plans'!B79+'Economic Expectations'!B79+'Real Sales Expectations'!B79) -> 89 | C79: =B79-B78 -> -6 | D79: =B79-B67 -> -8 | E79: 9637.732 | F79: =(E79-E67)/E67 -> 0.031695713
A80: ='NFIB SBO Core Index'!A80 -> 33816 | B80: =AVERAGE('Expansion Plans'!B80+'Employment Plans'!B80+'Inventory Plans'!B80+'Economic Expectations'!B80+'Real Sales Expectations'!B80) -> 64 | C80: =B80-B79 -> -25 | D80: =B80-B68 -> -34
A81: ='NFIB SBO Core Index'!A81 -> 33847 | B81: =AVERAGE('Expansion Plans'!B81+'Employment Plans'!B81+'Inventory Plans'!B81+'Economic Expectations'!B81+'Real Sales Expectations'!B81) -> 64 | C81: =B81-B80 -> 0 | D81: =B81-B69 -> -22
A82: ='NFIB SBO Core Index'!A82 -> 33877 | B82: =AVERAGE('Expansion Plans'!B82+'Employment Plans'!B82+'Inventory Plans'!B82+'Economic Expectations'!B82+'Real Sales Expectations'!B82) -> 57 | C82: =B82-B81 -> -7 | D82: =B82-B70 -> -23 | E82: 9732.979 | F82: =(E82-E70)/E70 -> 0.036653497
A83: ='NFIB SBO Core Index'!A83 -> 33908 | B83: =AVERAGE('Expansion Plans'!B83+'Employment Plans'!B83+'Inventory Plans'!B83+'Economic Expectations'!B83+'Real Sales Expectations'!B83) -> 51 | C83: =B83-B82 -> -6 | D83: =B83-B71 -> -21
A84: ='NFIB SBO Core Index'!A84 -> 33938 | B84: =AVERAGE('Expansion Plans'!B84+'Employment Plans'!B84+'Inventory Plans'!B84+'Economic Expectations'!B84+'Real Sales Expectations'!B84) -> 55 | C84: =B84-B83 -> 4 | D84: =B84-B72 -> 9
A85: ='NFIB SBO Core Index'!A85 -> 33969 | B85: =AVERAGE('Expansion Plans'!B85+'Employment Plans'!B85+'Inventory Plans'!B85+'Economic Expectations'!B85+'Real Sales Expectations'!B85) -> 70 | C85: =B85-B84 -> 15 | D85: =B85-B73 -> 19 | E85: 9834.51 | F85: =(E85-E73)/E73 -> 0.043829767
A86: ='NFIB SBO Core Index'!A86 -> 34000 | B86: =AVERAGE('Expansion Plans'!B86+'Employment Plans'!B86+'Inventory Plans'!B86+'Economic Expectations'!B86+'Real Sales Expectations'!B86) -> 68 | C86: =B86-B85 -> -2 | D86: =B86-B74 -> 2
A87: ='NFIB SBO Core Index'!A87 -> 34028 | B87: =AVERAGE('Expansion Plans'!B87+'Employment Plans'!B87+'Inventory Plans'!B87+'Economic Expectations'!B87+'Real Sales Expectations'!B87) -> 39 | C87: =B87-B86 -> -29 | D87: =B87-B75 -> -39
A88: ='NFIB SBO Core Index'!A88 -> 34059 | B88: =AVERAGE('Expansion Plans'!B88+'Employment Plans'!B88+'Inventory Plans'!B88+'Economic Expectations'!B88+'Real Sales Expectations'!B88) -> 20 | C88: =B88-B87 -> -19 | D88: =B88-B76 -> -78 | E88: 9850.973 | F88: =(E88-E76)/E76 -> 0.033209095
A89: ='NFIB SBO Core Index'!A89 -> 34089 | B89: =AVERAGE('Expansion Plans'!B89+'Employment Plans'!B89+'Inventory Plans'!B89+'Economic Expectations'!B89+'Real Sales Expectations'!B89) -> 8 | C89: =B89-B88 -> -12 | D89: =B89-B77 -> -91
A90: ='NFIB SBO Core Index'!A90 -> 34120 | B90: =AVERAGE('Expansion Plans'!B90+'Employment Plans'!B90+'Inventory Plans'!B90+'Economic Expectations'!B90+'Real Sales Expectations'!B90) -> -23 | C90: =B90-B89 -> -31 | D90: =B90-B78 -> -118
A91: ='NFIB SBO Core Index'!A91 -> 34150 | B91: =AVERAGE('Expansion Plans'!B91+'Employment Plans'!B91+'Inventory Plans'!B91+'Economic Expectations'!B91+'Real Sales Expectations'!B91) -> -26 | C91: =B91-B90 -> -3 | D91: =B91-B79 -> -115 | E91: 9908.347 | F91: =(E91-E79)/E79 -> 0.028078702
A92: ='NFIB SBO Core Index'!A92 -> 34181 | B92: =AVERAGE('Expansion Plans'!B92+'Employment Plans'!B92+'Inventory Plans'!B92+'Economic Expectations'!B92+'Real Sales Expectations'!B92) -> -18 | C92: =B92-B91 -> 8 | D92: =B92-B80 -> -82
A93: ='NFIB SBO Core Index'!A93 -> 34212 | B93: =AVERAGE('Expansion Plans'!B93+'Employment Plans'!B93+'Inventory Plans'!B93+'Economic Expectations'!B93+'Real Sales Expectations'!B93) -> -35 | C93: =B93-B92 -> -17 | D93: =B93-B81 -> -99
A94: ='NFIB SBO Core Index'!A94 -> 34242 | B94: =AVERAGE('Expansion Plans'!B94+'Employment Plans'!B94+'Inventory Plans'!B94+'Economic Expectations'!B94+'Real Sales Expectations'!B94) -> -17 | C94: =B94-B93 -> 18 | D94: =B94-B82 -> -74 | E94: 9955.641 | F94: =(E94-E82)/E82 -> 0.022877066
A95: ='NFIB SBO Core Index'!A95 -> 34273 | B95: =AVERAGE('Expansion Plans'!B95+'Employment Plans'!B95+'Inventory Plans'!B95+'Economic Expectations'!B95+'Real Sales Expectations'!B95) -> -10 | C95: =B95-B94 -> 7 | D95: =B95-B83 -> -61
A96: ='NFIB SBO Core Index'!A96 -> 34303 | B96: =AVERAGE('Expansion Plans'!B96+'Employment Plans'!B96+'Inventory Plans'!B96+'Economic Expectations'!B96+'Real Sales Expectations'!B96) -> 14 | C96: =B96-B95 -> 24 | D96: =B96-B84 -> -41
A97: ='NFIB SBO Core Index'!A97 -> 34334 | B97: =AVERAGE('Expansion Plans'!B97+'Employment Plans'!B97+'Inventory Plans'!B97+'Economic Expectations'!B97+'Real Sales Expectations'!B97) -> 24 | C97: =B97-B96 -> 10 | D97: =B97-B85 -> -46 | E97: 10091.049 | F97: =(E97-E85)/E85 -> 0.02608559
A98: ='NFIB SBO Core Index'!A98 -> 34365 | B98: =AVERAGE('Expansion Plans'!B98+'Employment Plans'!B98+'Inventory Plans'!B98+'Economic Expectations'!B98+'Real Sales Expectations'!B98) -> 41 | C98: =B98-B97 -> 17 | D98: =B98-B86 -> -27
A99: ='NFIB SBO Core Index'!A99 -> 34393 | B99: =AVERAGE('Expansion Plans'!B99+'Employment Plans'!B99+'Inventory Plans'!B99+'Economic Expectations'!B99+'Real Sales Expectations'!B99) -> 41 | C99: =B99-B98 -> 0 | D99: =B99-B87 -> 2
A100: ='NFIB SBO Core Index'!A100 -> 34424 | B100: =AVERAGE('Expansion Plans'!B100+'Employment Plans'!B100+'Inventory Plans'!B100+'Economic Expectations'!B100+'Real Sales Expectations'!B100) -> 42 | C100: =B100-B99 -> 1 | D100: =B100-B88 -> 22 | E100: 10188.954 | F100: =(E100-E88)/E88 -> 0.034309403
...

Sheet SBO_Leading_vs_SP500
A1: Date | B1: SBO - Leading Index | C1: SBO - Leading Index MoM | D1: SBO - Leading Index YoY | E1: S&P 500 Index | F1: S&P 500 Index YoY %
A2: 31443 | B2: =AVERAGE('Expansion Plans'!B2+'Employment Plans'!B2+'Inventory Plans'!B2+'Economic Expectations'!B2+'Real Sales Expectations'!B2) -> 57 | E2: 211.78
A3: 31471 | B3: =AVERAGE('Expansion Plans'!B3+'Employment Plans'!B3+'Inventory Plans'!B3+'Economic Expectations'!B3+'Real Sales Expectations'!B3) -> 56 | C3: =B3-B2 -> -1 | E3: 226.92
A4: 31502 | B4: =AVERAGE('Expansion Plans'!B4+'Employment Plans'!B4+'Inventory Plans'!B4+'Economic Expectations'!B4+'Real Sales Expectations'!B4) -> 78 | C4: =B4-B3 -> 22 | E4: 238.89999
A5: 31532 | B5: =AVERAGE('Expansion Plans'!B5+'Employment Plans'!B5+'Inventory Plans'!B5+'Economic Expectations'!B5+'Real Sales Expectations'!B5) -> 70 | C5: =B5-B4 -> -8 | E5: 235.52
A6: 31563 | B6: =AVERAGE('Expansion Plans'!B6+'Employment Plans'!B6+'Inventory Plans'!B6+'Economic Expectations'!B6+'Real Sales Expectations'!B6) -> 67 | C6: =B6-B5 -> -3 | E6: 247.35001
A7: 31593 | B7: =AVERAGE('Expansion Plans'!B7+'Employment Plans'!B7+'Inventory Plans'!B7+'Economic Expectations'!B7+'Real Sales Expectations'!B7) -> 71 | C7: =B7-B6 -> 4 | E7: 250.84
A8: 31624 | B8: =AVERAGE('Expansion Plans'!B8+'Employment Plans'!B8+'Inventory Plans'!B8+'Economic Expectations'!B8+'Real Sales Expectations'!B8) -> 50 | C8: =B8-B7 -> -21 | E8: 236.11999
A9: 31655 | B9: =AVERAGE('Expansion Plans'!B9+'Employment Plans'!B9+'Inventory Plans'!B9+'Economic Expectations'!B9+'Real Sales Expectations'!B9) -> 39 | C9: =B9-B8 -> -11 | E9: 252.92999
A10: 31685 | B10: =AVERAGE('Expansion Plans'!B10+'Employment Plans'!B10+'Inventory Plans'!B10+'Economic Expectations'!B10+'Real Sales Expectations'!B10) -> 36 | C10: =B10-B9 -> -3 | E10: 231.32001
A11: 31716 | B11: =AVERAGE('Expansion Plans'!B11+'Employment Plans'!B11+'Inventory Plans'!B11+'Economic Expectations'!B11+'Real Sales Expectations'!B11) -> 43 | C11: =B11-B10 -> 7 | E11: 243.98
A12: 31746 | B12: =AVERAGE('Expansion Plans'!B12+'Employment Plans'!B12+'Inventory Plans'!B12+'Economic Expectations'!B12+'Real Sales Expectations'!B12) -> 27 | C12: =B12-B11 -> -16 | E12: 249.22
A13: 31777 | B13: =AVERAGE('Expansion Plans'!B13+'Employment Plans'!B13+'Inventory Plans'!B13+'Economic Expectations'!B13+'Real Sales Expectations'!B13) -> 42 | C13: =B13-B12 -> 15 | E13: 242.17
A14: 31808 | B14: =AVERAGE('Expansion Plans'!B14+'Employment Plans'!B14+'Inventory Plans'!B14+'Economic Expectations'!B14+'Real Sales Expectations'!B14) -> 46 | C14: =B14-B13 -> 4 | D14: =B14-B2 -> -11 | E14: 274.07999 | F14: =(E14-E2)/E2 -> 0.29417314
A15: 31836 | B15: =AVERAGE('Expansion Plans'!B15+'Employment Plans'!B15+'Inventory Plans'!B15+'Economic Expectations'!B15+'Real Sales Expectations'!B15) -> 54 | C15: =B15-B14 -> 8 | D15: =B15-B3 -> -2 | E15: 284.20001 | F15: =(E15-E3)/E3 -> 0.25242383
A16: 31867 | B16: =AVERAGE('Expansion Plans'!B16+'Employment Plans'!B16+'Inventory Plans'!B16+'Economic Expectations'!B16+'Real Sales Expectations'!B16) -> 54 | C16: =B16-B15 -> 0 | D16: =B16-B4 -> -24 | E16: 291.70001 | F16: =(E16-E4)/E4 -> 0.22101306
A17: 31897 | B17: =AVERAGE('Expansion Plans'!B17+'Employment Plans'!B17+'Inventory Plans'!B17+'Economic Expectations'!B17+'Real Sales Expectations'!B17) -> 45 | C17: =B17-B16 -> -9 | D17: =B17-B5 -> -25 | E17: 288.35998 | F17: =(E17-E5)/E5 -> 0.22435454
A18: 31928 | B18: =AVERAGE('Expansion Plans'!B18+'Employment Plans'!B18+'Inventory Plans'!B18+'Economic Expectations'!B18+'Real Sales Expectations'!B18) -> 35 | C18: =B18-B17 -> -10 | D18: =B18-B6 -> -32 | E18: 290.10001 | F18: =(E18-E6)/E6 -> 0.17283202
A19: 31958 | B19: =AVERAGE('Expansion Plans'!B19+'Employment Plans'!B19+'Inventory Plans'!B19+'Economic Expectations'!B19+'Real Sales Expectations'!B19) -> 54 | C19: =B19-B18 -> 19 | D19: =B19-B7 -> -17 | E19: 304 | F19: =(E19-E7)/E7 -> 0.21192794
A20: 31989 | B20: =AVERAGE('Expansion Plans'!B20+'Employment Plans'!B20+'Inventory Plans'!B20+'Economic Expectations'!B20+'Real Sales Expectations'!B20) -> 54 | C20: =B20-B19 -> 0 | D20: =B20-B8 -> 4 | E20: 318.66 | F20: =(E20-E8)/E8 -> 0.34956806
A21: 32020 | B21: =AVERAGE('Expansion Plans'!B21+'Employment Plans'!B21+'Inventory Plans'!B21+'Economic Expectations'!B21+'Real Sales Expectations'!B21) -> 75 | C21: =B21-B20 -> 21 | D21: =B21-B9 -> 36 | E21: 329.79999 | F21: =(E21-E9)/E9 -> 0.30391807
A22: 32050 | B22: =AVERAGE('Expansion Plans'!B22+'Employment Plans'!B22+'Inventory Plans'!B22+'Economic Expectations'!B22+'Real Sales Expectations'!B22) -> 57 | C22: =B22-B21 -> -18 | D22: =B22-B10 -> 21 | E22: 321.82999 | F22: =(E22-E10)/E10 -> 0.39127606
A23: 32081 | B23: =AVERAGE('Expansion Plans'!B23+'Employment Plans'!B23+'Inventory Plans'!B23+'Economic Expectations'!B23+'Real Sales Expectations'!B23) -> 52 | C23: =B23-B22 -> -5 | D23: =B23-B11 -> 9 | E23: 251.78999 | F23: =(E23-E11)/E11 -> 0.032010809
A24: 32111 | B24: =AVERAGE('Expansion Plans'!B24+'Employment Plans'!B24+'Inventory Plans'!B24+'Economic Expectations'!B24+'Real Sales Expectations'!B24) -> 26 | C24: =B24-B23 -> -26 | D24: =B24-B12 -> -1 | E24: 230.3 | F24: =(E24-E12)/E12 -> -0.075916852
A25: 32142 | B25: =AVERAGE('Expansion Plans'!B25+'Employment Plans'!B25+'Inventory Plans'!B25+'Economic Expectations'!B25+'Real Sales Expectations'!B25) -> 24 | C25: =B25-B24 -> -2 | D25: =B25-B13 -> -18 | E25: 247.08 | F25: =(E25-E13)/E13 -> 0.02027503
... A421: 44196 | B421: =AVERAGE('Expansion Plans'!B421+'Employment Plans'!B421+'Inventory Plans'!B421+'Economic Expectations'!B421+'Real Sales Expectations'!B421) -> -5 | C421: =B421-B420 -> -57 | D421: =B421-B409 -> -80 | E421: 3756.0701 | F421: =(E421-E409)/E409 -> 0.16258923

Sheet Expansion Plans
B1: Now a Good Time to Expand | C1: =B1&" - 3mma" -> Now a Good Time to Expand - 3mma | D1: =B1&" YoY" -> Now a Good Time to Expand YoY | E1: =C1&" YoY" -> Now a Good Time to Expand - 3mma YoY
A2: 31443 | B2: 20 | G2: =B1&" - NFIB" -> Now a Good Time to Expand - NFIB | U2: =D1&" - NFIB" -> Now a Good Time to Expand YoY - NFIB
A3: 31471 | B3: 19
A4: 31502 | B4: 26 | C4: =AVERAGE(B2:B4) -> 21.666667
A5: 31532 | B5: 27 | C5: =AVERAGE(B3:B5) -> 24
A6: 31563 | B6: 26 | C6: =AVERAGE(B4:B6) -> 26.333333
A7: 31593 | B7: 23 | C7: =AVERAGE(B5:B7) -> 25.333333
A8: 31624 | B8: 20 | C8: =AVERAGE(B6:B8) -> 23
A9: 31655 | B9: 16 | C9: =AVERAGE(B7:B9) -> 19.666667
A10: 31685 | B10: 19 | C10: =AVERAGE(B8:B10) -> 18.333333
A11: 31716 | B11: 19 | C11: =AVERAGE(B9:B11) -> 18
A12: 31746 | B12: 16 | C12: =AVERAGE(B10:B12) -> 18
A13: 31777 | B13: 18 | C13: =AVERAGE(B11:B13) -> 17.666667
A14: 31808 | B14: 18 | C14: =AVERAGE(B12:B14) -> 17.333333 | D14: =B14-B2 -> -2
A15: 31836 | B15: 17 | C15: =AVERAGE(B13:B15) -> 17.666667 | D15: =B15-B3 -> -2
A16: 31867 | B16: 21 | C16: =AVERAGE(B14:B16) -> 18.666667 | D16: =B16-B4 -> -5 | E16: =C16-C4 -> -3
A17: 31897 | B17: 18 | C17: =AVERAGE(B15:B17) -> 18.666667 | D17: =B17-B5 -> -9 | E17: =C17-C5 -> -5.3333333
A18: 31928 | B18: 18 | C18: =AVERAGE(B16:B18) -> 19 | D18: =B18-B6 -> -8 | E18: =C18-C6 -> -7.3333333
A19: 31958 | B19: 20 | C19: =AVERAGE(B17:B19) -> 18.666667 | D19: =B19-B7 -> -3 | E19: =C19-C7 -> -6.6666667
A20: 31989 | B20: 19 | C20: =AVERAGE(B18:B20) -> 19 | D20: =B20-B8 -> -1 | E20: =C20-C8 -> -4
A21: 32020 | B21: 21 | C21: =AVERAGE(B19:B21) -> 20 | D21: =B21-B9 -> 5 | E21: =C21-C9 -> 0.33333333
A22: 32050 | B22: 21 | C22: =AVERAGE(B20:B22) -> 20.333333 | D22: =B22-B10 -> 2 | E22: =C22-C10 -> 2
A23: 32081 | B23: 18 | C23: =AVERAGE(B21:B23) -> 20 | D23: =B23-B11 -> -1 | E23: =C23-C11 -> 2
A24: 32111 | B24: 13 | C24: =AVERAGE(B22:B24) -> 17.333333 | D24: =B24-B12 -> -3 | E24: =C24-C12 -> -0.66666667
A25: 32142 | B25: 16 | C25: =AVERAGE(B23:B25) -> 15.666667 | D25: =B25-B13 -> -2 | E25: =C25-C13 -> -2
A26: 32173 | B26: 13 | C26: =AVERAGE(B24:B26) -> 14 | D26: =B26-B14 -> -5 | E26: =C26-C14 -> -3.3333333
A27: 32202 | B27: 15 | C27: =AVERAGE(B25:B27) -> 14.666667 | D27: =B27-B15 -> -2 | E27: =C27-C15 -> -3 | G27: =B1&" - NFIB - 2000-" -> Now a Good Time to Expand - NFIB - 2000- | U27: =D1&" - NFIB - 2000-" -> Now a Good Time to Expand YoY - NFIB - 2000-
A28: 32233 | B28: 18 | C28: =AVERAGE(B26:B28) -> 15.333333 | D28: =B28-B16 -> -3 | E28: =C28-C16 -> -3.3333333
A29: 32263 | B29: 20 | C29: =AVERAGE(B27:B29) -> 17.666667 | D29: =B29-B17 -> 2 | E29: =C29-C17 -> -1
A30: 32294 | B30: 19 | C30: =AVERAGE(B28:B30) -> 19 | D30: =B30-B18 -> 1 | E30: =C30-C18 -> 0
A31: 32324 | B31: 20 | C31: =AVERAGE(B29:B31) -> 19.666667 | D31: =B31-B19 -> 0 | E31: =C31-C19 -> 1
A32: 32355 | B32: 19 | C32: =AVERAGE(B30:B32) -> 19.333333 | D32: =B32-B20 -> 0 | E32: =C32-C20 -> 0.33333333
A33: 32386 | B33: 22 | C33: =AVERAGE(B31:B33) -> 20.333333 | D33: =B33-B21 -> 1 | E33: =C33-C21 -> 0.33333333
A34: 32416 | B34: 17 | C34: =AVERAGE(B32:B34) -> 19.333333 | D34: =B34-B22 -> -4 | E34: =C34-C22 -> -1
A35: 32447 | B35: 17 | C35: =AVERAGE(B33:B35) -> 18.666667 | D35: =B35-B23 -> -1 | E35: =C35-C23 -> -1.3333333
A36: 32477 | B36: 18 | C36: =AVERAGE(B34:B36) -> 17.333333 | D36: =B36-B24 -> 5 | E36: =C36-C24 -> 0
A37: 32508 | B37: 17 | C37: =AVERAGE(B35:B37) -> 17.333333 | D37: =B37-B25 -> 1 | E37: =C37-C25 -> 1.6666667
A38: 32539 | B38: 17 | C38: =AVERAGE(B36:B38) -> 17.333333 | D38: =B38-B26 -> 4 | E38: =C38-C26 -> 3.3333333
A39: 32567 | B39: 21 | C39: =AVERAGE(B37:B39) -> 18.333333 | D39: =B39-B27 -> 6 | E39: =C39-C27 -> 3.6666667
... A51: 32932 | B51: 12 | C51: =AVERAGE(B49:B51) -> 14.333333 | D51: =B51-B39 -> -9 | E51: =C51-C39 -> -4
A52: 32963 | B52: 15 | C52: =AVERAGE(B50:B52) -> 14 | D52: =B52-B40 -> -1 | E52: =C52-C40 -> -4 | G52: =C1&" - NFIB" -> Now a Good Time to Expand - 3mma - NFIB | U52: =E1&" - NFIB" -> Now a Good Time to Expand - 3mma YoY - NFIB
A53: 32993 | B53: 15 | C53: =AVERAGE(B51:B53) -> 14 | D53: =B53-B41 -> 1 | E53: =C53-C41 -> -3
A54: 33024 | B54: 16 | C54: =AVERAGE(B52:B54) -> 15.333333 | D54: =B54-B42 -> 1 | E54: =C54-C42 -> 0.33333333
A55: 33054 | B55: 16 | C55: =AVERAGE(B53:B55) -> 15.666667 | D55: =B55-B43 -> 0 | E55: =C55-C43 -> 0.66666667
A56: 33085 | B56: 13 | C56: =AVERAGE(B54:B56) -> 15 | D56: =B56-B44 -> -3 | E56: =C56-C44 -> -0.66666667
A57: 33116 | B57: 10 | C57: =AVERAGE(B55:B57) -> 13 | D57: =B57-B45 -> -6 | E57: =C57-C45 -> -3
A58: 33146 | B58: 9 | C58: =AVERAGE(B56:B58) -> 10.666667 | D58: =B58-B46 -> -12 | E58: =C58-C46 -> -7
A59: 33177 | B59: 7 | C59: =AVERAGE(B57:B59) -> 8.6666667 | D59: =B59-B47 -> -10 | E59: =C59-C47 -> -9.3333333
A60: 33207 | B60: 7 | C60: =AVERAGE(B58:B60) -> 7.6666667 | D60: =B60-B48 -> -6 | E60: =C60-C48 -> -9.3333333
A61: 33238 | B61: 7 | C61: =AVERAGE(B59:B61) -> 7 | D61: =B61-B49 -> -9 | E61: =C61-C49 -> -8.3333333
A62: 33269 | B62: 5 | C62: =AVERAGE(B60:B62) -> 6.3333333 | D62: =B62-B50 -> -10 | E62: =C62-C50 -> -8.3333333
A63: 33297 | B63: 9 | C63: =AVERAGE(B61:B63) -> 7 | D63: =B63-B51 -> -3 | E63: =C63-C51 -> -7.3333333
A64: 33328 | B64: 12 | C64: =AVERAGE(B62:B64) -> 8.6666667 | D64: =B64-B52 -> -3 | E64: =C64-C52 -> -5.3333333
... A421: 44196 | B421: 8 | C421: =AVERAGE(B419:B421) -> 10.666667 | D421: =B421-B409 -> -17 | E421: =C421-C409 -> -14.666667

Sheet Employment Plans
B1: Plans to Increase Employment | C1: =B1&" - 3mma" -> Plans to Increase Employment - 3mma | D1: =B1&" YoY" -> Plans to Increase Employment YoY | E1: =C1&" YoY" -> Plans to Increase Employment - 3mma YoY
A2: 31443 | B2: 9 | G2: =B1&" - NFIB" -> Plans to Increase Employment - NFIB | U2: =D1&" - NFIB" -> Plans to Increase Employment YoY - NFIB
A3: 31471 | B3: 7
A4: 31502 | B4: 13 | C4: =AVERAGE(B2:B4) -> 9.6666667
A5: 31532 | B5: 9 | C5: =AVERAGE(B3:B5) -> 9.6666667
A6: 31563 | B6: 9 | C6: =AVERAGE(B4:B6) -> 10.333333
A7: 31593 | B7: 10 | C7: =AVERAGE(B5:B7) -> 9.3333333
A8: 31624 | B8: 8 | C8: =AVERAGE(B6:B8) -> 9
A9: 31655 | B9: 5 | C9: =AVERAGE(B7:B9) -> 7.6666667
A10: 31685 | B10: 2 | C10: =AVERAGE(B8:B10) -> 5
A11: 31716 | B11: 7 | C11: =AVERAGE(B9:B11) -> 4.6666667
A12: 31746 | B12: 6 | C12: =AVERAGE(B10:B12) -> 5
A13: 31777 | B13: 9 | C13: =AVERAGE(B11:B13) -> 7.3333333
A14: 31808 | B14: 7 | C14: =AVERAGE(B12:B14) -> 7.3333333 | D14: =B14-B2 -> -2
A15: 31836 | B15: 7 | C15: =AVERAGE(B13:B15) -> 7.6666667 | D15: =B15-B3 -> 0
A16: 31867 | B16: 9 | C16: =AVERAGE(B14:B16) -> 7.6666667 | D16: =B16-B4 -> -4 | E16: =C16-C4 -> -2
A17: 31897 | B17: 10 | C17: =AVERAGE(B15:B17) -> 8.6666667 | D17: =B17-B5 -> 1 | E17: =C17-C5 -> -1
A18: 31928 | B18: 11 | C18: =AVERAGE(B16:B18) -> 10 | D18: =B18-B6 -> 2 | E18: =C18-C6 -> -0.33333333
A19: 31958 | B19: 11 | C19: =AVERAGE(B17:B19) -> 10.666667 | D19: =B19-B7 -> 1 | E19: =C19-C7 -> 1.3333333
A20: 31989 | B20: 10 | C20: =AVERAGE(B18:B20) -> 10.666667 | D20: =B20-B8 -> 2 | E20: =C20-C8 -> 1.6666667
A21: 32020 | B21: 14 | C21: =AVERAGE(B19:B21) -> 11.666667 | D21: =B21-B9 -> 9 | E21: =C21-C9 -> 4
A22: 32050 | B22: 11 | C22: =AVERAGE(B20:B22) -> 11.666667 | D22: =B22-B10 -> 9 | E22: =C22-C10 -> 6.6666667
A23: 32081 | B23: 10 | C23: =AVERAGE(B21:B23) -> 11.666667 | D23: =B23-B11 -> 3 | E23: =C23-C11 -> 7
A24: 32111 | B24: 9 | C24: =AVERAGE(B22:B24) -> 10 | D24: =B24-B12 -> 3 | E24: =C24-C12 -> 5
A25: 32142 | B25: 9 | C25: =AVERAGE(B23:B25) -> 9.3333333 | D25: =B25-B13 -> 0 | E25: =C25-C13 -> 2
A26: 32173 | B26: 12 | C26: =AVERAGE(B24:B26) -> 10 | D26: =B26-B14 -> 5 | E26: =C26-C14 -> 2.6666667
A27: 32202 | B27: 10 | C27: =AVERAGE(B25:B27) -> 10.333333 | D27: =B27-B15 -> 3 | E27: =C27-C15 -> 2.6666667 | G27: =B1&" - NFIB - 2000-" -> Plans to Increase Employment - NFIB - 2000- | U27: =D1&" - NFIB - 2000-" -> Plans to Increase Employment YoY - NFIB - 2000-
A28: 32233 | B28: 13 | C28: =AVERAGE(B26:B28) -> 11.666667 | D28: =B28-B16 -> 4 | E28: =C28-C16 -> 4
A29: 32263 | B29: 13 | C29: =AVERAGE(B27:B29) -> 12 | D29: =B29-B17 -> 3 | E29: =C29-C17 -> 3.3333333
A30: 32294 | B30: 11 | C30: =AVERAGE(B28:B30) -> 12.333333 | D30: =B30-B18 -> 0 | E30: =C30-C18 -> 2.3333333
A31: 32324 | B31: 12 | C31: =AVERAGE(B29:B31) -> 12 | D31: =B31-B19 -> 1 | E31: =C31-C19 -> 1.3333333
A32: 32355 | B32: 10 | C32: =AVERAGE(B30:B32) -> 11 | D32: =B32-B20 -> 0 | E32: =C32-C20 -> 0.33333333
A33: 32386 | B33: 12 | C33: =AVERAGE(B31:B33) -> 11.333333 | D33: =B33-B21 -> -2 | E33: =C33-C21 -> -0.33333333
A34: 32416 | B34: 14 | C34: =AVERAGE(B32:B34) -> 12 | D34: =B34-B22 -> 3 | E34: =C34-C22 -> 0.33333333
A35: 32447 | B35: 13 | C35: =AVERAGE(B33:B35) -> 13 | D35: =B35-B23 -> 3 | E35: =C35-C23 -> 1.3333333
A36: 32477 | B36: 11 | C36: =AVERAGE(B34:B36) -> 12.666667 | D36: =B36-B24 -> 2 | E36: =C36-C24 -> 2.6666667
A37: 32508 | B37: 11 | C37: =AVERAGE(B35:B37) -> 11.666667 | D37: =B37-B25 -> 2 | E37: =C37-C25 -> 2.3333333
A38: 32539 | B38: 11 | C38: =AVERAGE(B36:B38) -> 11 | D38: =B38-B26 -> -1 | E38: =C38-C26 -> 1
A39: 32567 | B39: 13 | C39: =AVERAGE(B37:B39) -> 11.666667 | D39: =B39-B27 -> 3 | E39: =C39-C27 -> 1.3333333
... A51: 32932 | B51: 11 | C51: =AVERAGE(B49:B51) -> 9.3333333 | D51: =B51-B39 -> -2 | E51: =C51-C39 -> -2.3333333
A52: 32963 | B52: 11 | C52: =AVERAGE(B50:B52) -> 10.333333 | D52: =B52-B40 -> -3 | E52: =C52-C40 -> -2.3333333 | G52: =C1&" - NFIB" -> Plans to Increase Employment - 3mma - NFIB | U52: =E1&" - NFIB" -> Plans to Increase Employment - 3mma YoY - NFIB
A53: 32993 | B53: 10 | C53: =AVERAGE(B51:B53) -> 10.666667 | D53: =B53-B41 -> -1 | E53: =C53-C41 -> -2
A54: 33024 | B54: 12 | C54: =AVERAGE(B52:B54) -> 11 | D54: =B54-B42 -> 1 | E54: =C54-C42 -> -1
A55: 33054 | B55: 10 | C55: =AVERAGE(B53:B55) -> 10.666667 | D55: =B55-B43 -> 3 | E55: =C55-C43 -> 1
A56: 33085 | B56: 9 | C56: =AVERAGE(B54:B56) -> 10.333333 | D56: =B56-B44 -> 1 | E56: =C56-C44 -> 1.6666667
A57: 33116 | B57: 6 | C57: =AVERAGE(B55:B57) -> 8.3333333 | D57: =B57-B45 -> 0 | E57: =C57-C45 -> 1.3333333
A58: 33146 | B58: 5 | C58: =AVERAGE(B56:B58) -> 6.6666667 | D58: =B58-B46 -> -4 | E58: =C58-C46 -> -1
A59: 33177 | B59: 4 | C59: =AVERAGE(B57:B59) -> 5 | D59: =B59-B47 -> -8 | E59: =C59-C47 -> -4
A60: 33207 | B60: 0 | C60: =AVERAGE(B58:B60) -> 3 | D60: =B60-B48 -> -10 | E60: =C60-C48 -> -7.3333333
A61: 33238 | B61: 0 | C61: =AVERAGE(B59:B61) -> 1.3333333 | D61: =B61-B49 -> -8 | E61: =C61-C49 -> -8.6666667
A62: 33269 | B62: 1 | C62: =AVERAGE(B60:B62) -> 0.33333333 | D62: =B62-B50 -> -8 | E62: =C62-C50 -> -8.6666667
A63: 33297 | B63: 4 | C63: =AVERAGE(B61:B63) -> 1.6666667 | D63: =B63-B51 -> -7 | E63: =C63-C51 -> -7.6666667
A64: 33328 | B64: 10 | C64: =AVERAGE(B62:B64) -> 5 | D64: =B64-B52 -> -1 | E64: =C64-C52 -> -5.3333333
... A421: 44196 | B421: 16 | C421: =AVERAGE(B419:B421) -> 18 | D421: =B421-B409 -> -2 | E421: =C421-C409 -> -0.66666667

Sheet Inventory Plans
B1: Plans to Increase Inventories | C1: =B1&" - 3mma" -> Plans to Increase Inventories - 3mma | D1: =B1&" YoY" -> Plans to Increase Inventories YoY | E1: =C1&" YoY" -> Plans to Increase Inventories - 3mma YoY
A2: 31443 | B2: 4 | G2: =B1&" - NFIB" -> Plans to Increase Inventories - NFIB | U2: =D1&" - NFIB" -> Plans to Increase Inventories YoY - NFIB
A3: 31471 | B3: 4
A4: 31502 | B4: 3 | C4: =AVERAGE(B2:B4) -> 3.6666667
A5: 31532 | B5: 2 | C5: =AVERAGE(B3:B5) -> 3
A6: 31563 | B6: 6 | C6: =AVERAGE(B4:B6) -> 3.6666667
A7: 31593 | B7: 4 | C7: =AVERAGE(B5:B7) -> 4
A8: 31624 | B8: 4 | C8: =AVERAGE(B6:B8) -> 4.6666667
A9: 31655 | B9: -2 | C9: =AVERAGE(B7:B9) -> 2
A10: 31685 | B10: 3 | C10: =AVERAGE(B8:B10) -> 1.6666667
A11: 31716 | B11: 3 | C11: =AVERAGE(B9:B11) -> 1.3333333
A12: 31746 | B12: -5 | C12: =AVERAGE(B10:B12) -> 0.33333333
A13: 31777 | B13: 5 | C13: =AVERAGE(B11:B13) -> 1
A14: 31808 | B14: 5 | C14: =AVERAGE(B12:B14) -> 1.6666667 | D14: =B14-B2 -> 1
A15: 31836 | B15: 6 | C15: =AVERAGE(B13:B15) -> 5.3333333 | D15: =B15-B3 -> 2
A16: 31867 | B16: 4 | C16: =AVERAGE(B14:B16) -> 5 | D16: =B16-B4 -> 1 | E16: =C16-C4 -> 1.3333333
A17: 31897 | B17: 5 | C17: =AVERAGE(B15:B17) -> 5 | D17: =B17-B5 -> 3 | E17: =C17-C5 -> 2
A18: 31928 | B18: 4 | C18: =AVERAGE(B16:B18) -> 4.3333333 | D18: =B18-B6 -> -2 | E18: =C18-C6 -> 0.66666667
A19: 31958 | B19: 5 | C19: =AVERAGE(B17:B19) -> 4.6666667 | D19: =B19-B7 -> 1 | E19: =C19-C7 -> 0.66666667
A20: 31989 | B20: 5 | C20: =AVERAGE(B18:B20) -> 4.6666667 | D20: =B20-B8 -> 1 | E20: =C20-C8 -> 0
A21: 32020 | B21: 8 | C21: =AVERAGE(B19:B21) -> 6 | D21: =B21-B9 -> 10 | E21: =C21-C9 -> 4
A22: 32050 | B22: 7 | C22: =AVERAGE(B20:B22) -> 6.6666667 | D22: =B22-B10 -> 4 | E22: =C22-C10 -> 5
A23: 32081 | B23: 6 | C23: =AVERAGE(B21:B23) -> 7 | D23: =B23-B11 -> 3 | E23: =C23-C11 -> 5.6666667
A24: 32111 | B24: 2 | C24: =AVERAGE(B22:B24) -> 5 | D24: =B24-B12 -> 7 | E24: =C24-C12 -> 4.6666667
A25: 32142 | B25: 7 | C25: =AVERAGE(B23:B25) -> 5 | D25: =B25-B13 -> 2 | E25: =C25-C13 -> 4
A26: 32173 | B26: 8 | C26: =AVERAGE(B24:B26) -> 5.6666667 | D26: =B26-B14 -> 3 | E26: =C26-C14 -> 4
A27: 32202 | B27: 3 | C27: =AVERAGE(B25:B27) -> 6 | D27: =B27-B15 -> -3 | E27: =C27-C15 -> 0.66666667 | G27: =B1&" - NFIB - 2000-" -> Plans to Increase Inventories - NFIB - 2000- | U27: =D1&" - NFIB - 2000-" -> Plans to Increase Inventories YoY - NFIB - 2000-
A28: 32233 | B28: 9 | C28: =AVERAGE(B26:B28) -> 6.6666667 | D28: =B28-B16 -> 5 | E28: =C28-C16 -> 1.6666667
A29: 32263 | B29: 4 | C29: =AVERAGE(B27:B29) -> 5.3333333 | D29: =B29-B17 -> -1 | E29: =C29-C17 -> 0.33333333
A30: 32294 | B30: 3 | C30: =AVERAGE(B28:B30) -> 5.3333333 | D30: =B30-B18 -> -1 | E30: =C30-C18 -> 1
A31: 32324 | B31: 6 | C31: =AVERAGE(B29:B31) -> 4.3333333 | D31: =B31-B19 -> 1 | E31: =C31-C19 -> -0.33333333
A32: 32355 | B32: 3 | C32: =AVERAGE(B30:B32) -> 4 | D32: =B32-B20 -> -2 | E32: =C32-C20 -> -0.66666667
A33: 32386 | B33: 6 | C33: =AVERAGE(B31:B33) -> 5 | D33: =B33-B21 -> -2 | E33: =C33-C21 -> -1
A34: 32416 | B34: 6 | C34: =AVERAGE(B32:B34) -> 5 | D34: =B34-B22 -> -1 | E34: =C34-C22 -> -1.6666667
A35: 32447 | B35: 4 | C35: =AVERAGE(B33:B35) -> 5.3333333 | D35: =B35-B23 -> -2 | E35: =C35-C23 -> -1.6666667
A36: 32477 | B36: 2 | C36: =AVERAGE(B34:B36) -> 4 | D36: =B36-B24 -> 0 | E36: =C36-C24 -> -1
A37: 32508 | B37: 3 | C37: =AVERAGE(B35:B37) -> 3 | D37: =B37-B25 -> -4 | E37: =C37-C25 -> -2
A38: 32539 | B38: 6 | C38: =AVERAGE(B36:B38) -> 3.6666667 | D38: =B38-B26 -> -2 | E38: =C38-C26 -> -2
A39: 32567 | B39: 9 | C39: =AVERAGE(B37:B39) -> 6 | D39: =B39-B27 -> 6 | E39: =C39-C27 -> 0
... A51: 32932 | B51: 6 | C51: =AVERAGE(B49:B51) -> 4.3333333 | D51: =B51-B39 -> -3 | E51: =C51-C39 -> -1.6666667
A52: 32963 | B52: 5 | C52: =AVERAGE(B50:B52) -> 5.3333333 | D52: =B52-B40 -> -5 | E52: =C52-C40 -> -3 | G52: =C1&" - NFIB" -> Plans to Increase Inventories - 3mma - NFIB | U52: =E1&" - NFIB" -> Plans to Increase Inventories - 3mma YoY - NFIB
A53: 32993 | B53: 4 | C53: =AVERAGE(B51:B53) -> 5 | D53: =B53-B41 -> -2 | E53: =C53-C41 -> -3.3333333
A54: 33024 | B54: 4 | C54: =AVERAGE(B52:B54) -> 4.3333333 | D54: =B54-B42 -> 5 | E54: =C54-C42 -> -0.66666667
A55: 33054 | B55: 2 | C55: =AVERAGE(B53:B55) -> 3.3333333 | D55: =B55-B43 -> -3 | E55: =C55-C43 -> 0
A56: 33085 | B56: 5 | C56: =AVERAGE(B54:B56) -> 3.6666667 | D56: =B56-B44 -> 2 | E56: =C56-C44 -> 1.3333333
A57: 33116 | B57: 3 | C57: =AVERAGE(B55:B57) -> 3.3333333 | D57: =B57-B45 -> 0 | E57: =C57-C45 -> -0.33333333
A58: 33146 | B58: -2 | C58: =AVERAGE(B56:B58) -> 2 | D58: =B58-B46 -> -4 | E58: =C58-C46 -> -0.66666667
A59: 33177 | B59: -1 | C59: =AVERAGE(B57:B59) -> 0 | D59: =B59-B47 -> -4 | E59: =C59-C47 -> -2.6666667
A60: 33207 | B60: 0 | C60: =AVERAGE(B58:B60) -> -1 | D60: =B60-B48 -> -9 | E60: =C60-C48 -> -5.6666667
A61: 33238 | B61: -1 | C61: =AVERAGE(B59:B61) -> -0.66666667 | D61: =B61-B49 -> -3 | E61: =C61-C49 -> -5.3333333
A62: 33269 | B62: -1 | C62: =AVERAGE(B60:B62) -> -0.66666667 | D62: =B62-B50 -> -6 | E62: =C62-C50 -> -6
A63: 33297 | B63: 3 | C63: =AVERAGE(B61:B63) -> 0.33333333 | D63: =B63-B51 -> -3 | E63: =C63-C51 -> -4
A64: 33328 | B64: 7 | C64: =AVERAGE(B62:B64) -> 3 | D64: =B64-B52 -> 2 | E64: =C64-C52 -> -2.3333333
... A421: 44196 | B421: 3 | C421: =AVERAGE(B419:B421) -> 6.3333333 | D421: =B421-B409 -> 1 | E421: =C421-C409 -> 3.3333333

Sheet Economic Expectations
B1: Expect Economy to Improve | C1: =B1&" - 3mma" -> Expect Economy to Improve - 3mma | D1: =B1&" YoY" -> Expect Economy to Improve YoY | E1: =C1&" YoY" -> Expect Economy to Improve - 3mma YoY
A2: 31443 | B2: 12 | G2: =B1&" - NFIB" -> Expect Economy to Improve - NFIB | U2: =D1&" - NFIB" -> Expect Economy to Improve YoY - NFIB
A3: 31471 | B3: 13
A4: 31502 | B4: 18 | C4: =AVERAGE(B2:B4) -> 14.333333
A5: 31532 | B5: 16 | C5: =AVERAGE(B3:B5) -> 15.666667
A6: 31563 | B6: 13 | C6: =AVERAGE(B4:B6) -> 15.666667
A7: 31593 | B7: 17 | C7: =AVERAGE(B5:B7) -> 15.333333
A8: 31624 | B8: 9 | C8: =AVERAGE(B6:B8) -> 13
A9: 31655 | B9: 10 | C9: =AVERAGE(B7:B9) -> 12
A10: 31685 | B10: 6 | C10: =AVERAGE(B8:B10) -> 8.3333333
A11: 31716 | B11: 7 | C11: =AVERAGE(B9:B11) -> 7.6666667
A12: 31746 | B12: 5 | C12: =AVERAGE(B10:B12) -> 6
A13: 31777 | B13: 5 | C13: =AVERAGE(B11:B13) -> 5.6666667
A14: 31808 | B14: 8 | C14: =AVERAGE(B12:B14) -> 6 | D14: =B14-B2 -> -4
A15: 31836 | B15: 12 | C15: =AVERAGE(B13:B15) -> 8.3333333 | D15: =B15-B3 -> -1
A16: 31867 | B16: 10 | C16: =AVERAGE(B14:B16) -> 10 | D16: =B16-B4 -> -8 | E16: =C16-C4 -> -4.3333333
A17: 31897 | B17: 6 | C17: =AVERAGE(B15:B17) -> 9.3333333 | D17: =B17-B5 -> -10 | E17: =C17-C5 -> -6.3333333
A18: 31928 | B18: 1 | C18: =AVERAGE(B16:B18) -> 5.6666667 | D18: =B18-B6 -> -12 | E18: =C18-C6 -> -10
A19: 31958 | B19: 9 | C19: =AVERAGE(B17:B19) -> 5.3333333 | D19: =B19-B7 -> -8 | E19: =C19-C7 -> -10
A20: 31989 | B20: 10 | C20: =AVERAGE(B18:B20) -> 6.6666667 | D20: =B20-B8 -> 1 | E20: =C20-C8 -> -6.3333333
A21: 32020 | B21: 16 | C21: =AVERAGE(B19:B21) -> 11.666667 | D21: =B21-B9 -> 6 | E21: =C21-C9 -> -0.33333333
A22: 32050 | B22: 9 | C22: =AVERAGE(B20:B22) -> 11.666667 | D22: =B22-B10 -> 3 | E22: =C22-C10 -> 3.3333333
A23: 32081 | B23: 9 | C23: =AVERAGE(B21:B23) -> 11.333333 | D23: =B23-B11 -> 2 | E23: =C23-C11 -> 3.6666667
A24: 32111 | B24: 1 | C24: =AVERAGE(B22:B24) -> 6.3333333 | D24: =B24-B12 -> -4 | E24: =C24-C12 -> 0.33333333
A25: 32142 | B25: -4 | C25: =AVERAGE(B23:B25) -> 2 | D25: =B25-B13 -> -9 | E25: =C25-C13 -> -3.6666667
A26: 32173 | B26: 1 | C26: =AVERAGE(B24:B26) -> -0.66666667 | D26: =B26-B14 -> -7 | E26: =C26-C14 -> -6.6666667
A27: 32202 | B27: 0 | C27: =AVERAGE(B25:B27) -> -1 | D27: =B27-B15 -> -12 | E27: =C27-C15 -> -9.3333333 | G27: =B1&" - NFIB - 2000-" -> Expect Economy to Improve - NFIB - 2000- | U27: =D1&" - NFIB - 2000-" -> Expect Economy to Improve YoY - NFIB - 2000-
A28: 32233 | B28: 6 | C28: =AVERAGE(B26:B28) -> 2.3333333 | D28: =B28-B16 -> -4 | E28: =C28-C16 -> -7.6666667
A29: 32263 | B29: 5 | C29: =AVERAGE(B27:B29) -> 3.6666667 | D29: =B29-B17 -> -1 | E29: =C29-C17 -> -5.6666667
A30: 32294 | B30: 0 | C30: =AVERAGE(B28:B30) -> 3.6666667 | D30: =B30-B18 -> -1 | E30: =C30-C18 -> -2
A31: 32324 | B31: 4 | C31: =AVERAGE(B29:B31) -> 3 | D31: =B31-B19 -> -5 | E31: =C31-C19 -> -2.3333333
A32: 32355 | B32: 1 | C32: =AVERAGE(B30:B32) -> 1.6666667 | D32: =B32-B20 -> -9 | E32: =C32-C20 -> -5
A33: 32386 | B33: 5 | C33: =AVERAGE(B31:B33) -> 3.3333333 | D33: =B33-B21 -> -11 | E33: =C33-C21 -> -8.3333333
A34: 32416 | B34: 2 | C34: =AVERAGE(B32:B34) -> 2.6666667 | D34: =B34-B22 -> -7 | E34: =C34-C22 -> -9
A35: 32447 | B35: 9 | C35: =AVERAGE(B33:B35) -> 5.3333333 | D35: =B35-B23 -> 0 | E35: =C35-C23 -> -6
A36: 32477 | B36: 8 | C36: =AVERAGE(B34:B36) -> 6.3333333 | D36: =B36-B24 -> 7 | E36: =C36-C24 -> 0
A37: 32508 | B37: 4 | C37: =AVERAGE(B35:B37) -> 7 | D37: =B37-B25 -> 8 | E37: =C37-C25 -> 5
A38: 32539 | B38: 4 | C38: =AVERAGE(B36:B38) -> 5.3333333 | D38: =B38-B26 -> 3 | E38: =C38-C26 -> 6
A39: 32567 | B39: 5 | C39: =AVERAGE(B37:B39) -> 4.3333333 | D39: =B39-B27 -> 5 | E39: =C39-C27 -> 5.3333333
... A51: 32932 | B51: 3 | C51: =AVERAGE(B49:B51) -> 4.3333333 | D51: =B51-B39 -> -2 | E51: =C51-C39 -> 0
A52: 32963 | B52: 5 | C52: =AVERAGE(B50:B52) -> 3.6666667 | D52: =B52-B40 -> 5 | E52: =C52-C40 -> 0.66666667 | G52: =C1&" - NFIB" -> Expect Economy to Improve - 3mma - NFIB | U52: =E1&" - NFIB" -> Expect Economy to Improve - 3mma YoY - NFIB
A53: 32993 | B53: 4 | C53: =AVERAGE(B51:B53) -> 4 | D53: =B53-B41 -> 10 | E53: =C53-C41 -> 4.3333333
A54: 33024 | B54: 1 | C54: =AVERAGE(B52:B54) -> 3.3333333 | D54: =B54-B42 -> 7 | E54: =C54-C42 -> 7.3333333
A55: 33054 | B55: 2 | C55: =AVERAGE(B53:B55) -> 2.3333333 | D55: =B55-B43 -> 1 | E55: =C55-C43 -> 6
A56: 33085 | B56: 0 | C56: =AVERAGE(B54:B56) -> 1 | D56: =B56-B44 -> 1 | E56: =C56-C44 -> 3
A57: 33116 | B57: -15 | C57: =AVERAGE(B55:B57) -> -4.3333333 | D57: =B57-B45 -> -23 | E57: =C57-C45 -> -7
A58: 33146 | B58: -16 | C58: =AVERAGE(B56:B58) -> -10.333333 | D58: =B58-B46 -> -29 | E58: =C58-C46 -> -17
A59: 33177 | B59: -26 | C59: =AVERAGE(B57:B59) -> -19 | D59: =B59-B47 -> -38 | E59: =C59-C47 -> -30
A60: 33207 | B60: -20 | C60: =AVERAGE(B58:B60) -> -20.666667 | D60: =B60-B48 -> -22 | E60: =C60-C48 -> -29.666667
A61: 33238 | B61: -8 | C61: =AVERAGE(B59:B61) -> -18 | D61: =B61-B49 -> -15 | E61: =C61-C49 -> -25
A62: 33269 | B62: -4 | C62: =AVERAGE(B60:B62) -> -10.666667 | D62: =B62-B50 -> -7 | E62: =C62-C50 -> -14.666667
A63: 33297 | B63: 22 | C63: =AVERAGE(B61:B63) -> 3.3333333 | D63: =B63-B51 -> 19 | E63: =C63-C51 -> -1
A64: 33328 | B64: 38 | C64: =AVERAGE(B62:B64) -> 18.666667 | D64: =B64-B52 -> 33 | E64: =C64-C52 -> 15
... A421: 44196 | B421: -16 | C421: =AVERAGE(B419:B421) -> 6.3333333 | D421: =B421-B409 -> -31 | E421: =C421-C409 -> -6.3333333

Sheet Real Sales Expectations
B1: Expect Real Sales to Improve | C1: =B1&" - 3mma" -> Expect Real Sales to Improve - 3mma | D1: =B1&" YoY" -> Expect Real Sales to Improve YoY | E1: =C1&" YoY" -> Expect Real Sales to Improve - 3mma YoY
A2: 31443 | B2: 12 | G2: =B1&" - NFIB" -> Expect Real Sales to Improve - NFIB | U2: =D1&" - NFIB" -> Expect Real Sales to Improve YoY - NFIB
A3: 31471 | B3: 13
A4: 31502 | B4: 18 | C4: =AVERAGE(B2:B4) -> 14.333333
A5: 31532 | B5: 16 | C5: =AVERAGE(B3:B5) -> 15.666667
A6: 31563 | B6: 13 | C6: =AVERAGE(B4:B6) -> 15.666667
A7: 31593 | B7: 17 | C7: =AVERAGE(B5:B7) -> 15.333333
A8: 31624 | B8: 9 | C8: =AVERAGE(B6:B8) -> 13
A9: 31655 | B9: 10 | C9: =AVERAGE(B7:B9) -> 12
A10: 31685 | B10: 6 | C10: =AVERAGE(B8:B10) -> 8.3333333
A11: 31716 | B11: 7 | C11: =AVERAGE(B9:B11) -> 7.6666667
A12: 31746 | B12: 5 | C12: =AVERAGE(B10:B12) -> 6
A13: 31777 | B13: 5 | C13: =AVERAGE(B11:B13) -> 5.6666667
A14: 31808 | B14: 8 | C14: =AVERAGE(B12:B14) -> 6 | D14: =B14-B2 -> -4
A15: 31836 | B15: 12 | C15: =AVERAGE(B13:B15) -> 8.3333333 | D15: =B15-B3 -> -1
A16: 31867 | B16: 10 | C16: =AVERAGE(B14:B16) -> 10 | D16: =B16-B4 -> -8 | E16: =C16-C4 -> -4.3333333
A17: 31897 | B17: 6 | C17: =AVERAGE(B15:B17) -> 9.3333333 | D17: =B17-B5 -> -10 | E17: =C17-C5 -> -6.3333333
A18: 31928 | B18: 1 | C18: =AVERAGE(B16:B18) -> 5.6666667 | D18: =B18-B6 -> -12 | E18: =C18-C6 -> -10
A19: 31958 | B19: 9 | C19: =AVERAGE(B17:B19) -> 5.3333333 | D19: =B19-B7 -> -8 | E19: =C19-C7 -> -10
A20: 31989 | B20: 10 | C20: =AVERAGE(B18:B20) -> 6.6666667 | D20: =B20-B8 -> 1 | E20: =C20-C8 -> -6.3333333
A21: 32020 | B21: 16 | C21: =AVERAGE(B19:B21) -> 11.666667 | D21: =B21-B9 -> 6 | E21: =C21-C9 -> -0.33333333
A22: 32050 | B22: 9 | C22: =AVERAGE(B20:B22) -> 11.666667 | D22: =B22-B10 -> 3 | E22: =C22-C10 -> 3.3333333
A23: 32081 | B23: 9 | C23: =AVERAGE(B21:B23) -> 11.333333 | D23: =B23-B11 -> 2 | E23: =C23-C11 -> 3.6666667
A24: 32111 | B24: 1 | C24: =AVERAGE(B22:B24) -> 6.3333333 | D24: =B24-B12 -> -4 | E24: =C24-C12 -> 0.33333333
A25: 32142 | B25: -4 | C25: =AVERAGE(B23:B25) -> 2 | D25: =B25-B13 -> -9 | E25: =C25-C13 -> -3.6666667
A26: 32173 | B26: 1 | C26: =AVERAGE(B24:B26) -> -0.66666667 | D26: =B26-B14 -> -7 | E26: =C26-C14 -> -6.6666667
A27: 32202 | B27: 0 | C27: =AVERAGE(B25:B27) -> -1 | D27: =B27-B15 -> -12 | E27: =C27-C15 -> -9.3333333 | G27: =B1&" - NFIB - 2000-" -> Expect Real Sales to Improve - NFIB - 2000- | U27: =D1&" - NFIB - 2000-" -> Expect Real Sales to Improve YoY - NFIB - 2000-
A28: 32233 | B28: 6 | C28: =AVERAGE(B26:B28) -> 2.3333333 | D28: =B28-B16 -> -4 | E28: =C28-C16 -> -7.6666667
A29: 32263 | B29: 5 | C29: =AVERAGE(B27:B29) -> 3.6666667 | D29: =B29-B17 -> -1 | E29: =C29-C17 -> -5.6666667
A30: 32294 | B30: 0 | C30: =AVERAGE(B28:B30) -> 3.6666667 | D30: =B30-B18 -> -1 | E30: =C30-C18 -> -2
A31: 32324 | B31: 4 | C31: =AVERAGE(B29:B31) -> 3 | D31: =B31-B19 -> -5 | E31: =C31-C19 -> -2.3333333
A32: 32355 | B32: 1 | C32: =AVERAGE(B30:B32) -> 1.6666667 | D32: =B32-B20 -> -9 | E32: =C32-C20 -> -5
A33: 32386 | B33: 5 | C33: =AVERAGE(B31:B33) -> 3.3333333 | D33: =B33-B21 -> -11 | E33: =C33-C21 -> -8.3333333
A34: 32416 | B34: 2 | C34: =AVERAGE(B32:B34) -> 2.6666667 | D34: =B34-B22 -> -7 | E34: =C34-C22 -> -9
A35: 32447 | B35: 9 | C35: =AVERAGE(B33:B35) -> 5.3333333 | D35: =B35-B23 -> 0 | E35: =C35-C23 -> -6
A36: 32477 | B36: 8 | C36: =AVERAGE(B34:B36) -> 6.3333333 | D36: =B36-B24 -> 7 | E36: =C36-C24 -> 0
A37: 32508 | B37: 4 | C37: =AVERAGE(B35:B37) -> 7 | D37: =B37-B25 -> 8 | E37: =C37-C25 -> 5
A38: 32539 | B38: 4 | C38: =AVERAGE(B36:B38) -> 5.3333333 | D38: =B38-B26 -> 3 | E38: =C38-C26 -> 6
A39: 32567 | B39: 5 | C39: =AVERAGE(B37:B39) -> 4.3333333 | D39: =B39-B27 -> 5 | E39: =C39-C27 -> 5.3333333
... A51: 32932 | B51: 3 | C51: =AVERAGE(B49:B51) -> 4.3333333 | D51: =B51-B39 -> -2 | E51: =C51-C39 -> 0
A52: 32963 | B52: 5 | C52: =AVERAGE(B50:B52) -> 3.6666667 | D52: =B52-B40 -> 5 | E52: =C52-C40 -> 0.66666667 | G52: =C1&" - NFIB" -> Expect Real Sales to Improve - 3mma - NFIB | U52: =E1&" - NFIB" -> Expect Real Sales to Improve - 3mma YoY - NFIB
A53: 32993 | B53: 4 | C53: =AVERAGE(B51:B53) -> 4 | D53: =B53-B41 -> 10 | E53: =C53-C41 -> 4.3333333
A54: 33024 | B54: 1 | C54: =AVERAGE(B52:B54) -> 3.3333333 | D54: =B54-B42 -> 7 | E54: =C54-C42 -> 7.3333333
A55: 33054 | B55: 2 | C55: =AVERAGE(B53:B55) -> 2.3333333 | D55: =B55-B43 -> 1 | E55: =C55-C43 -> 6
A56: 33085 | B56: 0 | C56: =AVERAGE(B54:B56) -> 1 | D56: =B56-B44 -> 1 | E56: =C56-C44 -> 3
A57: 33116 | B57: -15 | C57: =AVERAGE(B55:B57) -> -4.3333333 | D57: =B57-B45 -> -23 | E57: =C57-C45 -> -7
A58: 33146 | B58: -16 | C58: =AVERAGE(B56:B58) -> -10.333333 | D58: =B58-B46 -> -29 | E58: =C58-C46 -> -17
A59: 33177 | B59: -26 | C59: =AVERAGE(B57:B59) -> -19 | D59: =B59-B47 -> -38 | E59: =C59-C47 -> -30
A60: 33207 | B60: -20 | C60: =AVERAGE(B58:B60) -> -20.666667 | D60: =B60-B48 -> -22 | E60: =C60-C48 -> -29.666667
A61: 33238 | B61: -8 | C61: =AVERAGE(B59:B61) -> -18 | D61: =B61-B49 -> -15 | E61: =C61-C49 -> -25
A62: 33269 | B62: -4 | C62: =AVERAGE(B60:B62) -> -10.666667 | D62: =B62-B50 -> -7 | E62: =C62-C50 -> -14.666667
A63: 33297 | B63: 22 | C63: =AVERAGE(B61:B63) -> 3.3333333 | D63: =B63-B51 -> 19 | E63: =C63-C51 -> -1
A64: 33328 | B64: 38 | C64: =AVERAGE(B62:B64) -> 18.666667 | D64: =B64-B52 -> 33 | E64: =C64-C52 -> 15
... A421: 44196 | B421: -16 | C421: =AVERAGE(B419:B421) -> 6.3333333 | D421: =B421-B409 -> -31 | E421: =C421-C409 -> -6.3333333

Sheet Capital Plans
B1: Plans to Make Capital Outlays | C1: =B1&" - 3mma" -> Plans to Make Capital Outlays - 3mma | D1: =B1&" YoY" -> Plans to Make Capital Outlays YoY | E1: =C1&" YoY" -> Plans to Make Capital Outlays - 3mma YoY
A2: 31443 | B2: 31 | G2: =B1&" - NFIB" -> Plans to Make Capital Outlays - NFIB | U2: =D1&" - NFIB" -> Plans to Make Capital Outlays YoY - NFIB
A3: 31471 | B3: 29
A4: 31502 | B4: 28 | C4: =AVERAGE(B2:B4) -> 29.333333
A5: 31532 | B5: 32 | C5: =AVERAGE(B3:B5) -> 29.666667
A6: 31563 | B6: 34 | C6: =AVERAGE(B4:B6) -> 31.333333
A7: 31593 | B7: 30 | C7: =AVERAGE(B5:B7) -> 32
A8: 31624 | B8: 31 | C8: =AVERAGE(B6:B8) -> 31.666667
A9: 31655 | B9: 30 | C9: =AVERAGE(B7:B9) -> 30.333333
A10: 31685 | B10: 30 | C10: =AVERAGE(B8:B10) -> 30.333333
A11: 31716 | B11: 30 | C11: =AVERAGE(B9:B11) -> 30
A12: 31746 | B12: 28 | C12: =AVERAGE(B10:B12) -> 29.333333
A13: 31777 | B13: 29 | C13: =AVERAGE(B11:B13) -> 29
A14: 31808 | B14: 30 | C14: =AVERAGE(B12:B14) -> 29 | D14: =B14-B2 -> -1
A15: 31836 | B15: 29 | C15: =AVERAGE(B13:B15) -> 29.333333 | D15: =B15-B3 -> 0
A16: 31867 | B16: 33 | C16: =AVERAGE(B14:B16) -> 30.666667 | D16: =B16-B4 -> 5 | E16: =C16-C4 -> 1.3333333
A17: 31897 | B17: 31 | C17: =AVERAGE(B15:B17) -> 31 | D17: =B17-B5 -> -1 | E17: =C17-C5 -> 1.3333333
A18: 31928 | B18: 30 | C18: =AVERAGE(B16:B18) -> 31.333333 | D18: =B18-B6 -> -4 | E18: =C18-C6 -> 0
A19: 31958 | B19: 34 | C19: =AVERAGE(B17:B19) -> 31.666667 | D19: =B19-B7 -> 4 | E19: =C19-C7 -> -0.33333333
A20: 31989 | B20: 35 | C20: =AVERAGE(B18:B20) -> 33 | D20: =B20-B8 -> 4 | E20: =C20-C8 -> 1.3333333
A21: 32020 | B21: 32 | C21: =AVERAGE(B19:B21) -> 33.666667 | D21: =B21-B9 -> 2 | E21: =C21-C9 -> 3.3333333
A22: 32050 | B22: 31 | C22: =AVERAGE(B20:B22) -> 32.666667 | D22: =B22-B10 -> 1 | E22: =C22-C10 -> 2.3333333
A23: 32081 | B23: 31 | C23: =AVERAGE(B21:B23) -> 31.333333 | D23: =B23-B11 -> 1 | E23: =C23-C11 -> 1.3333333
A24: 32111 | B24: 29 | C24: =AVERAGE(B22:B24) -> 30.333333 | D24: =B24-B12 -> 1 | E24: =C24-C12 -> 1
A25: 32142 | B25: 30 | C25: =AVERAGE(B23:B25) -> 30 | D25: =B25-B13 -> 1 | E25: =C25-C13 -> 1
A26: 32173 | B26: 34 | C26: =AVERAGE(B24:B26) -> 31 | D26: =B26-B14 -> 4 | E26: =C26-C14 -> 2
A27: 32202 | B27: 32 | C27: =AVERAGE(B25:B27) -> 32 | D27: =B27-B15 -> 3 | E27: =C27-C15 -> 2.6666667 | G27: =B1&" - NFIB - 2000-" -> Plans to Make Capital Outlays - NFIB - 2000- | U27: =D1&" - NFIB - 2000-" -> Plans to Make Capital Outlays YoY - NFIB - 2000-
A28: 32233 | B28: 32 | C28: =AVERAGE(B26:B28) -> 32.666667 | D28: =B28-B16 -> -1 | E28: =C28-C16 -> 2
A29: 32263 | B29: 32 | C29: =AVERAGE(B27:B29) -> 32 | D29: =B29-B17 -> 1 | E29: =C29-C17 -> 1
A30: 32294 | B30: 33 | C30: =AVERAGE(B28:B30) -> 32.333333 | D30: =B30-B18 -> 3 | E30: =C30-C18 -> 1
A31: 32324 | B31: 31 | C31: =AVERAGE(B29:B31) -> 32 | D31: =B31-B19 -> -3 | E31: =C31-C19 -> 0.33333333
A32: 32355 | B32: 31 | C32: =AVERAGE(B30:B32) -> 31.666667 | D32: =B32-B20 -> -4 | E32: =C32-C20 -> -1.3333333
A33: 32386 | B33: 31 | C33: =AVERAGE(B31:B33) -> 31 | D33: =B33-B21 -> -1 | E33: =C33-C21 -> -2.6666667
A34: 32416 | B34: 32 | C34: =AVERAGE(B32:B34) -> 31.333333 | D34: =B34-B22 -> 1 | E34: =C34-C22 -> -1.3333333
A35: 32447 | B35: 35 | C35: =AVERAGE(B33:B35) -> 32.666667 | D35: =B35-B23 -> 4 | E35: =C35-C23 -> 1.3333333
A36: 32477 | B36: 34 | C36: =AVERAGE(B34:B36) -> 33.666667 | D36: =B36-B24 -> 5 | E36: =C36-C24 -> 3.3333333
A37: 32508 | B37: 33 | C37: =AVERAGE(B35:B37) -> 34 | D37: =B37-B25 -> 3 | E37: =C37-C25 -> 4
A38: 32539 | B38: 35 | C38: =AVERAGE(B36:B38) -> 34 | D38: =B38-B26 -> 1 | E38: =C38-C26 -> 3
A39: 32567 | B39: 32 | C39: =AVERAGE(B37:B39) -> 33.333333 | D39: =B39-B27 -> 0 | E39: =C39-C27 -> 1.3333333
... A51: 32932 | B51: 34 | C51: =AVERAGE(B49:B51) -> 33.666667 | D51: =B51-B39 -> 2 | E51: =C51-C39 -> 0.33333333
A52: 32963 | B52: 33 | C52: =AVERAGE(B50:B52) -> 33.666667 | D52: =B52-B40 -> -3 | E52: =C52-C40 -> -0.66666667 | G52: =C1&" - NFIB" -> Plans to Make Capital Outlays - 3mma - NFIB | U52: =E1&" - NFIB" -> Plans to Make Capital Outlays - 3mma YoY - NFIB
A53: 32993 | B53: 31 | C53: =AVERAGE(B51:B53) -> 32.666667 | D53: =B53-B41 -> -1 | E53: =C53-C41 -> -0.66666667
A54: 33024 | B54: 34 | C54: =AVERAGE(B52:B54) -> 32.666667 | D54: =B54-B42 -> 1 | E54: =C54-C42 -> -1
A55: 33054 | B55: 31 | C55: =AVERAGE(B53:B55) -> 32 | D55: =B55-B43 -> 1 | E55: =C55-C43 -> 0.33333333
A56: 33085 | B56: 31 | C56: =AVERAGE(B54:B56) -> 32 | D56: =B56-B44 -> -2 | E56: =C56-C44 -> 0
A57: 33116 | B57: 31 | C57: =AVERAGE(B55:B57) -> 31 | D57: =B57-B45 -> 0 | E57: =C57-C45 -> -0.33333333
A58: 33146 | B58: 28 | C58: =AVERAGE(B56:B58) -> 30 | D58: =B58-B46 -> -2 | E58: =C58-C46 -> -1.3333333
A59: 33177 | B59: 28 | C59: =AVERAGE(B57:B59) -> 29 | D59: =B59-B47 -> -4 | E59: =C59-C47 -> -2
A60: 33207 | B60: 30 | C60: =AVERAGE(B58:B60) -> 28.666667 | D60: =B60-B48 -> -2 | E60: =C60-C48 -> -2.6666667
A61: 33238 | B61: 26 | C61: =AVERAGE(B59:B61) -> 28 | D61: =B61-B49 -> -7 | E61: =C61-C49 -> -4.3333333
A62: 33269 | B62: 26 | C62: =AVERAGE(B60:B62) -> 27.333333 | D62: =B62-B50 -> -8 | E62: =C62-C50 -> -5.6666667
A63: 33297 | B63: 26 | C63: =AVERAGE(B61:B63) -> 26 | D63: =B63-B51 -> -8 | E63: =C63-C51 -> -7.6666667
A64: 33328 | B64: 26 | C64: =AVERAGE(B62:B64) -> 26 | D64: =B64-B52 -> -7 | E64: =C64-C52 -> -7.6666667
... A421: 44196 | B421: 22 | C421: =AVERAGE(B419:B421) -> 25 | D421: =B421-B409 -> -6 | E421: =C421-C409 -> -4

Sheet Current Inventory
B1: Current Inventory | C1: =B1&" - 3mma" -> Current Inventory - 3mma | D1: =B1&" YoY" -> Current Inventory YoY | E1: =C1&" YoY" -> Current Inventory - 3mma YoY
A2: 31443 | B2: -2 | G2: =B1&" - NFIB" -> Current Inventory - NFIB | U2: =D1&" - NFIB" -> Current Inventory YoY - NFIB
A3: 31471 | B3: -2
A4: 31502 | B4: -3 | C4: =AVERAGE(B2:B4) -> -2.3333333
A5: 31532 | B5: -3 | C5: =AVERAGE(B3:B5) -> -2.6666667
A6: 31563 | B6: 1 | C6: =AVERAGE(B4:B6) -> -1.6666667
A7: 31593 | B7: -4 | C7: =AVERAGE(B5:B7) -> -2
A8: 31624 | B8: -3 | C8: =AVERAGE(B6:B8) -> -2
A9: 31655 | B9: -4 | C9: =AVERAGE(B7:B9) -> -3.6666667
A10: 31685 | B10: -1 | C10: =AVERAGE(B8:B10) -> -2.6666667
A11: 31716 | B11: -2 | C11: =AVERAGE(B9:B11) -> -2.3333333
A12: 31746 | B12: -6 | C12: =AVERAGE(B10:B12) -> -3
A13: 31777 | B13: -1 | C13: =AVERAGE(B11:B13) -> -3
A14: 31808 | B14: -3 | C14: =AVERAGE(B12:B14) -> -3.3333333 | D14: =B14-B2 -> -1
A15: 31836 | B15: -2 | C15: =AVERAGE(B13:B15) -> -2 | D15: =B15-B3 -> 0
A16: 31867 | B16: 0 | C16: =AVERAGE(B14:B16) -> -1.6666667 | D16: =B16-B4 -> 3 | E16: =C16-C4 -> 0.66666667
A17: 31897 | B17: -1 | C17: =AVERAGE(B15:B17) -> -1 | D17: =B17-B5 -> 2 | E17: =C17-C5 -> 1.6666667
A18: 31928 | B18: -1 | C18: =AVERAGE(B16:B18) -> -0.66666667 | D18: =B18-B6 -> -2 | E18: =C18-C6 -> 1
A19: 31958 | B19: -3 | C19: =AVERAGE(B17:B19) -> -1.6666667 | D19: =B19-B7 -> 1 | E19: =C19-C7 -> 0.33333333
A20: 31989 | B20: 0 | C20: =AVERAGE(B18:B20) -> -1.3333333 | D20: =B20-B8 -> 3 | E20: =C20-C8 -> 0.66666667
A21: 32020 | B21: -1 | C21: =AVERAGE(B19:B21) -> -1.3333333 | D21: =B21-B9 -> 3 | E21: =C21-C9 -> 2.3333333
A22: 32050 | B22: -1 | C22: =AVERAGE(B20:B22) -> -0.66666667 | D22: =B22-B10 -> 0 | E22: =C22-C10 -> 2
A23: 32081 | B23: 0 | C23: =AVERAGE(B21:B23) -> -0.66666667 | D23: =B23-B11 -> 2 | E23: =C23-C11 -> 1.6666667
A24: 32111 | B24: -2 | C24: =AVERAGE(B22:B24) -> -1 | D24: =B24-B12 -> 4 | E24: =C24-C12 -> 2
A25: 32142 | B25: 0 | C25: =AVERAGE(B23:B25) -> -0.66666667 | D25: =B25-B13 -> 1 | E25: =C25-C13 -> 2.3333333
A26: 32173 | B26: -5 | C26: =AVERAGE(B24:B26) -> -2.3333333 | D26: =B26-B14 -> -2 | E26: =C26-C14 -> 1
A27: 32202 | B27: -3 | C27: =AVERAGE(B25:B27) -> -2.6666667 | D27: =B27-B15 -> -1 | E27: =C27-C15 -> -0.66666667 | G27: =B1&" - NFIB - 2000-" -> Current Inventory - NFIB - 2000- | U27: =D1&" - NFIB - 2000-" -> Current Inventory YoY - NFIB - 2000-
A28: 32233 | B28: -1 | C28: =AVERAGE(B26:B28) -> -3 | D28: =B28-B16 -> -1 | E28: =C28-C16 -> -1.3333333
A29: 32263 | B29: -2 | C29: =AVERAGE(B27:B29) -> -2 | D29: =B29-B17 -> -1 | E29: =C29-C17 -> -1
A30: 32294 | B30: -2 | C30: =AVERAGE(B28:B30) -> -1.6666667 | D30: =B30-B18 -> -1 | E30: =C30-C18 -> -1
A31: 32324 | B31: -2 | C31: =AVERAGE(B29:B31) -> -2 | D31: =B31-B19 -> 1 | E31: =C31-C19 -> -0.33333333
A32: 32355 | B32: -2 | C32: =AVERAGE(B30:B32) -> -2 | D32: =B32-B20 -> -2 | E32: =C32-C20 -> -0.66666667
A33: 32386 | B33: -4 | C33: =AVERAGE(B31:B33) -> -2.6666667 | D33: =B33-B21 -> -3 | E33: =C33-C21 -> -1.3333333
A34: 32416 | B34: -3 | C34: =AVERAGE(B32:B34) -> -3 | D34: =B34-B22 -> -2 | E34: =C34-C22 -> -2.3333333
A35: 32447 | B35: 0 | C35: =AVERAGE(B33:B35) -> -2.3333333 | D35: =B35-B23 -> 0 | E35: =C35-C23 -> -1.6666667
A36: 32477 | B36: -2 | C36: =AVERAGE(B34:B36) -> -1.6666667 | D36: =B36-B24 -> 0 | E36: =C36-C24 -> -0.66666667
A37: 32508 | B37: -5 | C37: =AVERAGE(B35:B37) -> -2.3333333 | D37: =B37-B25 -> -5 | E37: =C37-C25 -> -1.6666667
A38: 32539 | B38: -2 | C38: =AVERAGE(B36:B38) -> -3 | D38: =B38-B26 -> 3 | E38: =C38-C26 -> -0.66666667
A39: 32567 | B39: -2 | C39: =AVERAGE(B37:B39) -> -3 | D39: =B39-B27 -> 1 | E39: =C39-C27 -> -0.33333333
... A51: 32932 | B51: -3 | C51: =AVERAGE(B49:B51) -> -3.3333333 | D51: =B51-B39 -> -1 | E51: =C51-C39 -> -0.33333333
A52: 32963 | B52: 1 | C52: =AVERAGE(B50:B52) -> -2 | D52: =B52-B40 -> 2 | E52: =C52-C40 -> -0.33333333 | G52: =C1&" - NFIB" -> Current Inventory - 3mma - NFIB | U52: =E1&" - NFIB" -> Current Inventory - 3mma YoY - NFIB
A53: 32993 | B53: 0 | C53: =AVERAGE(B51:B53) -> -0.66666667 | D53: =B53-B41 -> 1 | E53: =C53-C41 -> 0.66666667
A54: 33024 | B54: -2 | C54: =AVERAGE(B52:B54) -> -0.33333333 | D54: =B54-B42 -> 0 | E54: =C54-C42 -> 1
A55: 33054 | B55: -3 | C55: =AVERAGE(B53:B55) -> -1.6666667 | D55: =B55-B43 -> -2 | E55: =C55-C43 -> -0.33333333
A56: 33085 | B56: -3 | C56: =AVERAGE(B54:B56) -> -2.6666667 | D56: =B56-B44 -> -1 | E56: =C56-C44 -> -1
A57: 33116 | B57: -3 | C57: =AVERAGE(B55:B57) -> -3 | D57: =B57-B45 -> -2 | E57: =C57-C45 -> -1.6666667
A58: 33146 | B58: -6 | C58: =AVERAGE(B56:B58) -> -4 | D58: =B58-B46 -> -6 | E58: =C58-C46 -> -3
A59: 33177 | B59: -3 | C59: =AVERAGE(B57:B59) -> -4 | D59: =B59-B47 -> -1 | E59: =C59-C47 -> -3
A60: 33207 | B60: -3 | C60: =AVERAGE(B58:B60) -> -4 | D60: =B60-B48 -> -3 | E60: =C60-C48 -> -3.3333333
A61: 33238 | B61: -6 | C61: =AVERAGE(B59:B61) -> -4 | D61: =B61-B49 -> -3 | E61: =C61-C49 -> -2.3333333
A62: 33269 | B62: -4 | C62: =AVERAGE(B60:B62) -> -4.3333333 | D62: =B62-B50 -> 0 | E62: =C62-C50 -> -2
A63: 33297 | B63: -6 | C63: =AVERAGE(B61:B63) -> -5.3333333 | D63: =B63-B51 -> -3 | E63: =C63-C51 -> -2
A64: 33328 | B64: -1 | C64: =AVERAGE(B62:B64) -> -3.6666667 | D64: =B64-B52 -> -2 | E64: =C64-C52 -> -1.6666667
... A421: 44196 | B421: 6 | C421: =AVERAGE(B419:B421) -> 5 | D421: =B421-B409 -> 10 | E421: =C421-C409 -> 7.3333333

Sheet Current Job Openings
B1: Current Job Openings | C1: =B1&" - 3mma" -> Current Job Openings - 3mma | D1: =B1&" YoY" -> Current Job Openings YoY | E1: =C1&" YoY" -> Current Job Openings - 3mma YoY
A2: 31443 | B2: 18 | G2: =B1&" - NFIB" -> Current Job Openings - NFIB | U2: =D1&" - NFIB" -> Current Job Openings YoY - NFIB
A3: 31471 | B3: 15
A4: 31502 | B4: 19 | C4: =AVERAGE(B2:B4) -> 17.333333
A5: 31532 | B5: 16 | C5: =AVERAGE(B3:B5) -> 16.666667
A6: 31563 | B6: 15 | C6: =AVERAGE(B4:B6) -> 16.666667
A7: 31593 | B7: 18 | C7: =AVERAGE(B5:B7) -> 16.333333
A8: 31624 | B8: 16 | C8: =AVERAGE(B6:B8) -> 16.333333
A9: 31655 | B9: 16 | C9: =AVERAGE(B7:B9) -> 16.666667
A10: 31685 | B10: 14 | C10: =AVERAGE(B8:B10) -> 15.333333
A11: 31716 | B11: 17 | C11: =AVERAGE(B9:B11) -> 15.666667
A12: 31746 | B12: 18 | C12: =AVERAGE(B10:B12) -> 16.333333
A13: 31777 | B13: 17 | C13: =AVERAGE(B11:B13) -> 17.333333
A14: 31808 | B14: 17 | C14: =AVERAGE(B12:B14) -> 17.333333 | D14: =B14-B2 -> -1
A15: 31836 | B15: 20 | C15: =AVERAGE(B13:B15) -> 18 | D15: =B15-B3 -> 5
A16: 31867 | B16: 18 | C16: =AVERAGE(B14:B16) -> 18.333333 | D16: =B16-B4 -> -1 | E16: =C16-C4 -> 1
A17: 31897 | B17: 19 | C17: =AVERAGE(B15:B17) -> 19 | D17: =B17-B5 -> 3 | E17: =C17-C5 -> 2.3333333
A18: 31928 | B18: 21 | C18: =AVERAGE(B16:B18) -> 19.333333 | D18: =B18-B6 -> 6 | E18: =C18-C6 -> 2.6666667
A19: 31958 | B19: 17 | C19: =AVERAGE(B17:B19) -> 19 | D19: =B19-B7 -> -1 | E19: =C19-C7 -> 2.6666667
A20: 31989 | B20: 19 | C20: =AVERAGE(B18:B20) -> 19 | D20: =B20-B8 -> 3 | E20: =C20-C8 -> 2.6666667
A21: 32020 | B21: 21 | C21: =AVERAGE(B19:B21) -> 19 | D21: =B21-B9 -> 5 | E21: =C21-C9 -> 2.3333333
A22: 32050 | B22: 19 | C22: =AVERAGE(B20:B22) -> 19.666667 | D22: =B22-B10 -> 5 | E22: =C22-C10 -> 4.3333333
A23: 32081 | B23: 19 | C23: =AVERAGE(B21:B23) -> 19.666667 | D23: =B23-B11 -> 2 | E23: =C23-C11 -> 4
A24: 32111 | B24: 22 | C24: =AVERAGE(B22:B24) -> 20 | D24: =B24-B12 -> 4 | E24: =C24-C12 -> 3.6666667
A25: 32142 | B25: 22 | C25: =AVERAGE(B23:B25) -> 21 | D25: =B25-B13 -> 5 | E25: =C25-C13 -> 3.6666667
A26: 32173 | B26: 25 | C26: =AVERAGE(B24:B26) -> 23 | D26: =B26-B14 -> 8 | E26: =C26-C14 -> 5.6666667
A27: 32202 | B27: 20 | C27: =AVERAGE(B25:B27) -> 22.333333 | D27: =B27-B15 -> 0 | E27: =C27-C15 -> 4.3333333 | G27: =B1&" - NFIB - 2000-" -> Current Job Openings - NFIB - 2000- | U27: =D1&" - NFIB - 2000-" -> Current Job Openings YoY - NFIB - 2000-
A28: 32233 | B28: 18 | C28: =AVERAGE(B26:B28) -> 21 | D28: =B28-B16 -> 0 | E28: =C28-C16 -> 2.6666667
A29: 32263 | B29: 21 | C29: =AVERAGE(B27:B29) -> 19.666667 | D29: =B29-B17 -> 2 | E29: =C29-C17 -> 0.66666667
A30: 32294 | B30: 21 | C30: =AVERAGE(B28:B30) -> 20 | D30: =B30-B18 -> 0 | E30: =C30-C18 -> 0.66666667
A31: 32324 | B31: 20 | C31: =AVERAGE(B29:B31) -> 20.666667 | D31: =B31-B19 -> 3 | E31: =C31-C19 -> 1.6666667
A32: 32355 | B32: 20 | C32: =AVERAGE(B30:B32) -> 20.333333 | D32: =B32-B20 -> 1 | E32: =C32-C20 -> 1.3333333
A33: 32386 | B33: 23 | C33: =AVERAGE(B31:B33) -> 21 | D33: =B33-B21 -> 2 | E33: =C33-C21 -> 2
A34: 32416 | B34: 23 | C34: =AVERAGE(B32:B34) -> 22 | D34: =B34-B22 -> 4 | E34: =C34-C22 -> 2.3333333
A35: 32447 | B35: 24 | C35: =AVERAGE(B33:B35) -> 23.333333 | D35: =B35-B23 -> 5 | E35: =C35-C23 -> 3.6666667
A36: 32477 | B36: 23 | C36: =AVERAGE(B34:B36) -> 23.333333 | D36: =B36-B24 -> 1 | E36: =C36-C24 -> 3.3333333
A37: 32508 | B37: 24 | C37: =AVERAGE(B35:B37) -> 23.666667 | D37: =B37-B25 -> 2 | E37: =C37-C25 -> 2.6666667
A38: 32539 | B38: 25 | C38: =AVERAGE(B36:B38) -> 24 | D38: =B38-B26 -> 0 | E38: =C38-C26 -> 1
A39: 32567 | B39: 24 | C39: =AVERAGE(B37:B39) -> 24.333333 | D39: =B39-B27 -> 4 | E39: =C39-C27 -> 2
... A51: 32932 | B51: 21 | C51: =AVERAGE(B49:B51) -> 21.333333 | D51: =B51-B39 -> -3 | E51: =C51-C39 -> -3
A52: 32963 | B52: 19 | C52: =AVERAGE(B50:B52) -> 21 | D52: =B52-B40 -> -5 | E52: =C52-C40 -> -3.3333333 | G52: =C1&" - NFIB" -> Current Job Openings - 3mma - NFIB | U52: =E1&" - NFIB" -> Current Job Openings - 3mma YoY - NFIB
A53: 32993 | B53: 20 | C53: =AVERAGE(B51:B53) -> 20 | D53: =B53-B41 -> -3 | E53: =C53-C41 -> -3.6666667
A54: 33024 | B54: 22 | C54: =AVERAGE(B52:B54) -> 20.333333 | D54: =B54-B42 -> 0 | E54: =C54-C42 -> -2.6666667
A55: 33054 | B55: 19 | C55: =AVERAGE(B53:B55) -> 20.333333 | D55: =B55-B43 -> -4 | E55: =C55-C43 -> -2.3333333
A56: 33085 | B56: 19 | C56: =AVERAGE(B54:B56) -> 20 | D56: =B56-B44 -> -4 | E56: =C56-C44 -> -2.6666667
A57: 33116 | B57: 19 | C57: =AVERAGE(B55:B57) -> 19 | D57: =B57-B45 -> 1 | E57: =C57-C45 -> -2.3333333
A58: 33146 | B58: 19 | C58: =AVERAGE(B56:B58) -> 19 | D58: =B58-B46 -> -3 | E58: =C58-C46 -> -2
A59: 33177 | B59: 18 | C59: =AVERAGE(B57:B59) -> 18.666667 | D59: =B59-B47 -> -4 | E59: =C59-C47 -> -2
A60: 33207 | B60: 18 | C60: =AVERAGE(B58:B60) -> 18.333333 | D60: =B60-B48 -> -7 | E60: =C60-C48 -> -4.6666667
A61: 33238 | B61: 15 | C61: =AVERAGE(B59:B61) -> 17 | D61: =B61-B49 -> -5 | E61: =C61-C49 -> -5.3333333
A62: 33269 | B62: 15 | C62: =AVERAGE(B60:B62) -> 16 | D62: =B62-B50 -> -8 | E62: =C62-C50 -> -6.6666667
A63: 33297 | B63: 14 | C63: =AVERAGE(B61:B63) -> 14.666667 | D63: =B63-B51 -> -7 | E63: =C63-C51 -> -6.6666667
A64: 33328 | B64: 16 | C64: =AVERAGE(B62:B64) -> 15 | D64: =B64-B52 -> -3 | E64: =C64-C52 -> -6
... A421: 44196 | B421: 32 | C421: =AVERAGE(B419:B421) -> 33 | D421: =B421-B409 -> -1 | E421: =C421-C409 -> -2

Sheet Credit Expectations
B1: Expected Credit Conditions | C1: =B1&" - 3mma" -> Expected Credit Conditions - 3mma | D1: =B1&" YoY" -> Expected Credit Conditions YoY | E1: =C1&" YoY" -> Expected Credit Conditions - 3mma YoY
A2: 31443 | B2: -5 | G2: =B1&" - NFIB" -> Expected Credit Conditions - NFIB | U2: =D1&" - NFIB" -> Expected Credit Conditions YoY - NFIB
A3: 31471 | B3: -7
A4: 31502 | B4: -5 | C4: =AVERAGE(B2:B4) -> -5.6666667
A5: 31532 | B5: -4 | C5: =AVERAGE(B3:B5) -> -5.3333333
A6: 31563 | B6: -1 | C6: =AVERAGE(B4:B6) -> -3.3333333
A7: 31593 | B7: -6 | C7: =AVERAGE(B5:B7) -> -3.6666667
A8: 31624 | B8: -6 | C8: =AVERAGE(B6:B8) -> -4.3333333
A9: 31655 | B9: -7 | C9: =AVERAGE(B7:B9) -> -6.3333333
A10: 31685 | B10: -6 | C10: =AVERAGE(B8:B10) -> -6.3333333
A11: 31716 | B11: -7 | C11: =AVERAGE(B9:B11) -> -6.6666667
A12: 31746 | B12: -7 | C12: =AVERAGE(B10:B12) -> -6.6666667
A13: 31777 | B13: -4 | C13: =AVERAGE(B11:B13) -> -6
A14: 31808 | B14: -5 | C14: =AVERAGE(B12:B14) -> -5.3333333 | D14: =B14-B2 -> 0
A15: 31836 | B15: -6 | C15: =AVERAGE(B13:B15) -> -5 | D15: =B15-B3 -> 1
A16: 31867 | B16: -5 | C16: =AVERAGE(B14:B16) -> -5.3333333 | D16: =B16-B4 -> 0 | E16: =C16-C4 -> 0.33333333
A17: 31897 | B17: -6 | C17: =AVERAGE(B15:B17) -> -5.6666667 | D17: =B17-B5 -> -2 | E17: =C17-C5 -> -0.33333333
A18: 31928 | B18: -8 | C18: =AVERAGE(B16:B18) -> -6.3333333 | D18: =B18-B6 -> -7 | E18: =C18-C6 -> -3
A19: 31958 | B19: -6 | C19: =AVERAGE(B17:B19) -> -6.6666667 | D19: =B19-B7 -> 0 | E19: =C19-C7 -> -3
A20: 31989 | B20: -6 | C20: =AVERAGE(B18:B20) -> -6.6666667 | D20: =B20-B8 -> 0 | E20: =C20-C8 -> -2.3333333
A21: 32020 | B21: -6 | C21: =AVERAGE(B19:B21) -> -6 | D21: =B21-B9 -> 1 | E21: =C21-C9 -> 0.33333333
A22: 32050 | B22: -6 | C22: =AVERAGE(B20:B22) -> -6 | D22: =B22-B10 -> 0 | E22: =C22-C10 -> 0.33333333
A23: 32081 | B23: -7 | C23: =AVERAGE(B21:B23) -> -6.3333333 | D23: =B23-B11 -> 0 | E23: =C23-C11 -> 0.33333333
A24: 32111 | B24: -7 | C24: =AVERAGE(B22:B24) -> -6.6666667 | D24: =B24-B12 -> 0 | E24: =C24-C12 -> 0
A25: 32142 | B25: -5 | C25: =AVERAGE(B23:B25) -> -6.3333333 | D25: =B25-B13 -> -1 | E25: =C25-C13 -> -0.33333333
A26: 32173 | B26: -7 | C26: =AVERAGE(B24:B26) -> -6.3333333 | D26: =B26-B14 -> -2 | E26: =C26-C14 -> -1
A27: 32202 | B27: -4 | C27: =AVERAGE(B25:B27) -> -5.3333333 | D27: =B27-B15 -> 2 | E27: =C27-C15 -> -0.33333333 | G27: =B1&" - NFIB - 2000-" -> Expected Credit Conditions - NFIB - 2000- | U27: =D1&" - NFIB - 2000-" -> Expected Credit Conditions YoY - NFIB - 2000-
A28: 32233 | B28: -4 | C28: =AVERAGE(B26:B28) -> -5 | D28: =B28-B16 -> 1 | E28: =C28-C16 -> 0.33333333
A29: 32263 | B29: -6 | C29: =AVERAGE(B27:B29) -> -4.6666667 | D29: =B29-B17 -> 0 | E29: =C29-C17 -> 1
A30: 32294 | B30: -9 | C30: =AVERAGE(B28:B30) -> -6.3333333 | D30: =B30-B18 -> -1 | E30: =C30-C18 -> 0
A31: 32324 | B31: -6 | C31: =AVERAGE(B29:B31) -> -7 | D31: =B31-B19 -> 0 | E31: =C31-C19 -> -0.33333333
A32: 32355 | B32: -6 | C32: =AVERAGE(B30:B32) -> -7 | D32: =B32-B20 -> 0 | E32: =C32-C20 -> -0.33333333
A33: 32386 | B33: -5 | C33: =AVERAGE(B31:B33) -> -5.6666667 | D33: =B33-B21 -> 1 | E33: =C33-C21 -> 0.33333333
A34: 32416 | B34: -9 | C34: =AVERAGE(B32:B34) -> -6.6666667 | D34: =B34-B22 -> -3 | E34: =C34-C22 -> -0.66666667
A35: 32447 | B35: -7 | C35: =AVERAGE(B33:B35) -> -7 | D35: =B35-B23 -> 0 | E35: =C35-C23 -> -0.66666667
A36: 32477 | B36: -8 | C36: =AVERAGE(B34:B36) -> -8 | D36: =B36-B24 -> -1 | E36: =C36-C24 -> -1.3333333
A37: 32508 | B37: -10 | C37: =AVERAGE(B35:B37) -> -8.3333333 | D37: =B37-B25 -> -5 | E37: =C37-C25 -> -2
A38: 32539 | B38: -7 | C38: =AVERAGE(B36:B38) -> -8.3333333 | D38: =B38-B26 -> 0 | E38: =C38-C26 -> -2
A39: 32567 | B39: -9 | C39: =AVERAGE(B37:B39) -> -8.6666667 | D39: =B39-B27 -> -5 | E39: =C39-C27 -> -3.3333333
... A51: 32932 | B51: -7 | C51: =AVERAGE(B49:B51) -> -6.6666667 | D51: =B51-B39 -> 2 | E51: =C51-C39 -> 2
A52: 32963 | B52: -8 | C52: =AVERAGE(B50:B52) -> -7 | D52: =B52-B40 -> 1 | E52: =C52-C40 -> 1.3333333 | G52: =C1&" - NFIB" -> Expected Credit Conditions - 3mma - NFIB | U52: =E1&" - NFIB" -> Expected Credit Conditions - 3mma YoY - NFIB
A53: 32993 | B53: -8 | C53: =AVERAGE(B51:B53) -> -7.6666667 | D53: =B53-B41 -> 4 | E53: =C53-C41 -> 2.3333333
A54: 33024 | B54: -11 | C54: =AVERAGE(B52:B54) -> -9 | D54: =B54-B42 -> -1 | E54: =C54-C42 -> 1.3333333
A55: 33054 | B55: -10 | C55: =AVERAGE(B53:B55) -> -9.6666667 | D55: =B55-B43 -> -3 | E55: =C55-C43 -> 0
A56: 33085 | B56: -11 | C56: =AVERAGE(B54:B56) -> -10.666667 | D56: =B56-B44 -> -5 | E56: =C56-C44 -> -3
A57: 33116 | B57: -13 | C57: =AVERAGE(B55:B57) -> -11.333333 | D57: =B57-B45 -> -7 | E57: =C57-C45 -> -5
A58: 33146 | B58: -12 | C58: =AVERAGE(B56:B58) -> -12 | D58: =B58-B46 -> -5 | E58: =C58-C46 -> -5.6666667
A59: 33177 | B59: -13 | C59: =AVERAGE(B57:B59) -> -12.666667 | D59: =B59-B47 -> -7 | E59: =C59-C47 -> -6.3333333
A60: 33207 | B60: -14 | C60: =AVERAGE(B58:B60) -> -13 | D60: =B60-B48 -> -7 | E60: =C60-C48 -> -6.3333333
A61: 33238 | B61: -13 | C61: =AVERAGE(B59:B61) -> -13.333333 | D61: =B61-B49 -> -6 | E61: =C61-C49 -> -6.6666667
A62: 33269 | B62: -12 | C62: =AVERAGE(B60:B62) -> -13 | D62: =B62-B50 -> -6 | E62: =C62-C50 -> -6.3333333
A63: 33297 | B63: -10 | C63: =AVERAGE(B61:B63) -> -11.666667 | D63: =B63-B51 -> -3 | E63: =C63-C51 -> -5
A64: 33328 | B64: -10 | C64: =AVERAGE(B62:B64) -> -10.666667 | D64: =B64-B52 -> -2 | E64: =C64-C52 -> -3.6666667
... A421: 44196 | B421: -5 | C421: =AVERAGE(B419:B421) -> -4 | D421: =B421-B409 -> -2 | E421: =C421-C409 -> -1

Sheet Earnings Trend
B1: Earnings Trend | C1: =B1&" - 3mma" -> Earnings Trend - 3mma | D1: =B1&" YoY" -> Earnings Trend YoY | E1: =C1&" YoY" -> Earnings Trend - 3mma YoY
A2: 31443 | B2: -12 | G2: =B1&" - NFIB" -> Earnings Trend - NFIB | U2: =D1&" - NFIB" -> Earnings Trend YoY - NFIB
A3: 31471 | B3: -12
A4: 31502 | B4: -10 | C4: =AVERAGE(B2:B4) -> -11.333333
A5: 31532 | B5: -12 | C5: =AVERAGE(B3:B5) -> -11.333333
A6: 31563 | B6: -10 | C6: =AVERAGE(B4:B6) -> -10.666667
A7: 31593 | B7: -7 | C7: =AVERAGE(B5:B7) -> -9.6666667
A8: 31624 | B8: -10 | C8: =AVERAGE(B6:B8) -> -9
A9: 31655 | B9: -15 | C9: =AVERAGE(B7:B9) -> -10.666667
A10: 31685 | B10: -14 | C10: =AVERAGE(B8:B10) -> -13
A11: 31716 | B11: -8 | C11: =AVERAGE(B9:B11) -> -12.333333
A12: 31746 | B12: -15 | C12: =AVERAGE(B10:B12) -> -12.333333
A13: 31777 | B13: -5 | C13: =AVERAGE(B11:B13) -> -9.3333333
A14: 31808 | B14: -8 | C14: =AVERAGE(B12:B14) -> -9.3333333 | D14: =B14-B2 -> 4
A15: 31836 | B15: -11 | C15: =AVERAGE(B13:B15) -> -8 | D15: =B15-B3 -> 1
A16: 31867 | B16: -7 | C16: =AVERAGE(B14:B16) -> -8.6666667 | D16: =B16-B4 -> 3 | E16: =C16-C4 -> 2.6666667
A17: 31897 | B17: -10 | C17: =AVERAGE(B15:B17) -> -9.3333333 | D17: =B17-B5 -> 2 | E17: =C17-C5 -> 2
A18: 31928 | B18: -9 | C18: =AVERAGE(B16:B18) -> -8.6666667 | D18: =B18-B6 -> 1 | E18: =C18-C6 -> 2
A19: 31958 | B19: -7 | C19: =AVERAGE(B17:B19) -> -8.6666667 | D19: =B19-B7 -> 0 | E19: =C19-C7 -> 1
A20: 31989 | B20: -7 | C20: =AVERAGE(B18:B20) -> -7.6666667 | D20: =B20-B8 -> 3 | E20: =C20-C8 -> 1.3333333
A21: 32020 | B21: -5 | C21: =AVERAGE(B19:B21) -> -6.3333333 | D21: =B21-B9 -> 10 | E21: =C21-C9 -> 4.3333333
A22: 32050 | B22: -2 | C22: =AVERAGE(B20:B22) -> -4.6666667 | D22: =B22-B10 -> 12 | E22: =C22-C10 -> 8.3333333
A23: 32081 | B23: -7 | C23: =AVERAGE(B21:B23) -> -4.6666667 | D23: =B23-B11 -> 1 | E23: =C23-C11 -> 7.6666667
A24: 32111 | B24: -10 | C24: =AVERAGE(B22:B24) -> -6.3333333 | D24: =B24-B12 -> 5 | E24: =C24-C12 -> 6
A25: 32142 | B25: -7 | C25: =AVERAGE(B23:B25) -> -8 | D25: =B25-B13 -> -2 | E25: =C25-C13 -> 1.3333333
A26: 32173 | B26: -6 | C26: =AVERAGE(B24:B26) -> -7.6666667 | D26: =B26-B14 -> 2 | E26: =C26-C14 -> 1.6666667
A27: 32202 | B27: -12 | C27: =AVERAGE(B25:B27) -> -8.3333333 | D27: =B27-B15 -> -1 | E27: =C27-C15 -> -0.33333333 | G27: =B1&" - NFIB - 2000-" -> Earnings Trend - NFIB - 2000- | U27: =D1&" - NFIB - 2000-" -> Earnings Trend YoY - NFIB - 2000-
A28: 32233 | B28: -3 | C28: =AVERAGE(B26:B28) -> -7 | D28: =B28-B16 -> 4 | E28: =C28-C16 -> 1.6666667
A29: 32263 | B29: -9 | C29: =AVERAGE(B27:B29) -> -8 | D29: =B29-B17 -> 1 | E29: =C29-C17 -> 1.3333333
A30: 32294 | B30: -7 | C30: =AVERAGE(B28:B30) -> -6.3333333 | D30: =B30-B18 -> 2 | E30: =C30-C18 -> 2.3333333
A31: 32324 | B31: -4 | C31: =AVERAGE(B29:B31) -> -6.6666667 | D31: =B31-B19 -> 3 | E31: =C31-C19 -> 2
A32: 32355 | B32: -7 | C32: =AVERAGE(B30:B32) -> -6 | D32: =B32-B20 -> 0 | E32: =C32-C20 -> 1.6666667
A33: 32386 | B33: -8 | C33: =AVERAGE(B31:B33) -> -6.3333333 | D33: =B33-B21 -> -3 | E33: =C33-C21 -> 0
A34: 32416 | B34: -10 | C34: =AVERAGE(B32:B34) -> -8.3333333 | D34: =B34-B22 -> -8 | E34: =C34-C22 -> -3.6666667
A35: 32447 | B35: -8 | C35: =AVERAGE(B33:B35) -> -8.6666667 | D35: =B35-B23 -> -1 | E35: =C35-C23 -> -4
A36: 32477 | B36: -10 | C36: =AVERAGE(B34:B36) -> -9.3333333 | D36: =B36-B24 -> 0 | E36: =C36-C24 -> -3
A37: 32508 | B37: -9 | C37: =AVERAGE(B35:B37) -> -9 | D37: =B37-B25 -> -2 | E37: =C37-C25 -> -1
A38: 32539 | B38: -5 | C38: =AVERAGE(B36:B38) -> -8 | D38: =B38-B26 -> 1 | E38: =C38-C26 -> -0.33333333
A39: 32567 | B39: -7 | C39: =AVERAGE(B37:B39) -> -7 | D39: =B39-B27 -> 5 | E39: =C39-C27 -> 1.3333333
... A51: 32932 | B51: -14 | C51: =AVERAGE(B49:B51) -> -11.333333 | D51: =B51-B39 -> -7 | E51: =C51-C39 -> -4.3333333
A52: 32963 | B52: -9 | C52: =AVERAGE(B50:B52) -> -12 | D52: =B52-B40 -> -2 | E52: =C52-C40 -> -5.6666667 | G52: =C1&" - NFIB" -> Earnings Trend - 3mma - NFIB | U52: =E1&" - NFIB" -> Earnings Trend - 3mma YoY - NFIB
A53: 32993 | B53: -12 | C53: =AVERAGE(B51:B53) -> -11.666667 | D53: =B53-B41 -> 1 | E53: =C53-C41 -> -2.6666667
A54: 33024 | B54: -10 | C54: =AVERAGE(B52:B54) -> -10.333333 | D54: =B54-B42 -> 4 | E54: =C54-C42 -> 1
A55: 33054 | B55: -12 | C55: =AVERAGE(B53:B55) -> -11.333333 | D55: =B55-B43 -> 3 | E55: =C55-C43 -> 2.6666667
A56: 33085 | B56: -13 | C56: =AVERAGE(B54:B56) -> -11.666667 | D56: =B56-B44 -> -3 | E56: =C56-C44 -> 1.3333333
A57: 33116 | B57: -16 | C57: =AVERAGE(B55:B57) -> -13.666667 | D57: =B57-B45 -> -6 | E57: =C57-C45 -> -2
A58: 33146 | B58: -20 | C58: =AVERAGE(B56:B58) -> -16.333333 | D58: =B58-B46 -> -11 | E58: =C58-C46 -> -6.6666667
A59: 33177 | B59: -24 | C59: =AVERAGE(B57:B59) -> -20 | D59: =B59-B47 -> -12 | E59: =C59-C47 -> -9.6666667
A60: 33207 | B60: -22 | C60: =AVERAGE(B58:B60) -> -22 | D60: =B60-B48 -> -7 | E60: =C60-C48 -> -10
A61: 33238 | B61: -26 | C61: =AVERAGE(B59:B61) -> -24 | D61: =B61-B49 -> -19 | E61: =C61-C49 -> -12.666667
A62: 33269 | B62: -24 | C62: =AVERAGE(B60:B62) -> -24 | D62: =B62-B50 -> -11 | E62: =C62-C50 -> -12.333333
A63: 33297 | B63: -21 | C63: =AVERAGE(B61:B63) -> -23.666667 | D63: =B63-B51 -> -7 | E63: =C63-C51 -> -12.333333
A64: 33328 | B64: -23 | C64: =AVERAGE(B62:B64) -> -22.666667 | D64: =B64-B52 -> -14 | E64: =C64-C52 -> -10.666667
... A421: 44196 | B421: -14 | C421: =AVERAGE(B419:B421) -> -8 | D421: =B421-B409 -> -6 | E421: =C421-C409 -> -3.3333333
